Workbook

Sheet Master
A1: 246 South 2nd Street · Master Pro Forma
A2: 246 South 2nd Street on its own 3,100 sf lot in R6 with a commercial overlay: 8 stories at 85 ft (13'-11" ground floor, 11 ft 2nd floor, 10 ft above), plus a cellar and a private roof. 9 condos (8 market-rate and one affordable homeownership unit), 6,879 sellable sf; commercial on the 1st and 2nd floors (4,333 sf sellable) plus 1,857 sf in the cellar; Zone Green (ULEB) 5% exclusion; no air rights or certificates; all-electric. Residential priced at $1,450/sf (base, placeholder until comps).
A3: Every figure here is pulled from the Finance, Hard Costs and Soft Costs sheets (green). Change inputs on those sheets, not here.
A5: PROGRAM
A6: Condo units | B6: ='Hard Costs'!$C$12 -> 9
A7: Net sellable residential sf, as designed | B7: ='Hard Costs'!$C$10 -> 6879 | E7: The real area. Costs and the $ / sellable sf column use it.
A8: Sellable sf used for revenue | B8: ='Rev & Unit-by-Unit'!$I$27 -> 6879 | E8: Includes the owner's sellable-area adjustment (revenue only) on the Rev & Unit-by-Unit sheet.
A9: Commercial at grade (1st floor), sf | B9: ='Hard Costs'!$C$9 -> 1717
A10: Commercial, 2nd floor, sf | B10: ='Hard Costs'!$C$22 -> 2616
A11: Cellar commercial and community facility, sf | B11: ='Hard Costs'!$C$17 -> 1857 | E11: Sold with the commercial condo. Not zoning floor area.
A12: Gross floor area above grade | B12: ='Hard Costs'!$C$6 -> 14518 | E12: Plus a cellar; see the Hard Costs sheet.
A13: Zoning floor area check (total, with the Zone Green exclusion) | B13: ='Hard Costs'!C49 -> PASS | E13: From the Hard Costs sheet: 11,911 of 14,880 sf counted.
A14: Market-rate residential floor area check | B14: ='Hard Costs'!C50 -> PASS | E14: 6,819 counted of 6,820 allowed (2.2 FAR), after the Zone Green exclusion.
A15: Height check: 85 ft against the 85 ft limit | B15: ='Hard Costs'!C54 -> PASS
A17: REVENUE
B18: Amount | C18: $ / sellable sf | D18: % of cost | E18: Notes
A19: Residential condo sales, gross | B19: ='Rev & Unit-by-Unit'!$M$27 -> 9030450 | C19: =B19/$B$7 -> 1312.7562 | E19: Sum of the unit prices on the Rev & Unit-by-Unit sheet.
A20: Average condo price, all units | B20: ='Rev & Unit-by-Unit'!$N$27 -> 1312.7562 | E20: $ per sellable sf used for revenue.
A21: Price, standard units | B21: ='Rev & Unit-by-Unit'!$G$6 -> 1450 | E21: Before any unit premium, discount or asking-price override.
A22: Commercial condo sale value | B22: ='Rev & Unit-by-Unit'!$G$42 -> 5095798 | C22: =B22/($B$9+$B$10) -> 1176.0438 | E22: Value per sf of commercial above grade (1st and 2nd floors). Rent, vacancy, expenses and cap rate on the Rev & Unit-by-Unit sheet.
A23: Gross revenue | B23: =B19+B22 -> 14126248 | C23: =B23/$B$7 -> 2053.5322
A24: Less condo sale costs | B24: =-'Rev & Unit-by-Unit'!$M$61 -> -518219.21 | C24: =B24/$B$7 -> -75.33351 | E24: Commissions, transfer taxes paid by the sponsor, closing costs.
A25: Less commercial sale costs | B25: =-'Rev & Unit-by-Unit'!$M$68 -> -498114.25 | C25: =B25/$B$7 -> -72.410853
A26: Less end-loan packages and lender releases | B26: =-'Rev & Unit-by-Unit'!$M$74 -> -34000 | C26: =B26/$B$7 -> -4.9425789
A27: Net revenue | B27: ='Rev & Unit-by-Unit'!$M$78 -> 13075915 | C27: =B27/$B$7 -> 1900.8453
A29: PROJECT COSTS
B30: Amount | C30: $ / sellable sf | D30: % of cost | E30: Notes
A31: Land | B31: ='Soft Costs'!$C$7 -> 4000000 | C31: =B31/$B$7 -> 581.47987 | D31: =B31/$B$40 -> 0.30537787
A32: Inclusionary Housing certificates (none) | B32: ='Soft Costs'!$G$24 -> 0 | C32: =B32/$B$7 -> 0 | D32: =B32/$B$40 -> 0 | E32: Not needed: the affordable floor area is the on-site unit.
A33: Hard costs | B33: ='Hard Costs'!$G$121 -> 6533100 | C33: =B33/$B$7 -> 949.71653 | D33: =B33/$B$40 -> 0.49876604 | E33: Owner's $450 per gsf above grade; the line items at 725 Grand rates come to about $471/gsf (Hard Costs sheet).
A34: Soft costs, construction period | B34: ='Soft Costs'!$G$49 -> 1549116.8 | C34: =B34/$B$7 -> 225.19506 | D34: =B34/$B$40 -> 0.1182665 | E34: Before the mortgage recording tax; line by line on the Soft Costs sheet.
A35: Mortgage recording tax on the construction loan | B35: ='Soft Costs'!$G$51 -> 260492.59 | C35: =B35/$B$7 -> 37.8678 | D35: =B35/$B$40 -> 0.019887168
A36: Loan origination fee | B36: =Finance!$B$39 -> 93033.069 | C36: =B36/$B$7 -> 13.524214 | D36: =B36/$B$40 -> 0.0071025602
A37: Construction loan interest | B37: =Finance!$B$47 -> 600118.08 | C37: =B37/$B$7 -> 87.239146 | D37: =B37/$B$40 -> 0.045815696 | E37: From the monthly cash flow on the Finance sheet.
A38: Equity placement fee | B38: =Finance!$B$42 -> 0 | C38: =B38/$B$7 -> 0 | D38: =B38/$B$40 -> 0
A39: Sponsor wind-down | B39: ='Soft Costs'!$G$59 -> 62665.5 | C39: =B39/$B$7 -> 9.1096816 | D39: =B39/$B$40 -> 0.0047841642 | E39: Board turnover, warranty reserve, final audit and dissolution, on the Soft Costs sheet.
A40: Total project cost | B40: =SUM(B31:B39) -> 13098526 | C40: =B40/$B$7 -> 1904.1323 | D40: =B40/$B$40 -> 1
A42: PROFIT
A43: Profit | B43: =B27-B40 -> -22611.515 | C43: =B43/$B$7 -> -3.2870352
A44: Margin on cost | B44: =B43/B40 -> -0.0017262641 | E44: Profit ÷ total project cost.
A45: Profit per unit | B45: =B43/B6 -> -2512.3906
A46: Check: Finance sheet profit less this profit (should be 0) | B46: =Finance!$B$52-B43 -> 2.7939677e-09
A47: of which from the sellable-area adjustment | B47: ='Rev & Unit-by-Unit'!$M$82 -> 0 | E47: Off in this case.
A48: of which from commercial at 0% vacancy | B48: ='Rev & Unit-by-Unit'!$M$83 -> 236994.01 | E48: Compared with 5% vacancy, net of commercial sale costs.
A49: Profit without these two adjustments | B49: =B43-B47-B48 -> -259605.52 | E49: What a lender or appraiser measuring the real areas might see. Approximate: interest held fixed.
A50: Margin on cost without them | B50: =B49/B40 -> -0.019819445
A52: CAPITAL
A53: Construction loan commitment | B53: =Finance!$B$38 -> 9303306.9
A54: Peak loan balance | B54: =Finance!$B$48 -> 8634237.7
A55: Equity invested | B55: =Finance!$B$50 -> 4401622.9 | E55: Goes in first, before any loan draws.
A57: RETURNS
A58: Equity multiple | B58: =Finance!$B$54 -> 0.99486291
A59: Cash-on-cash return, whole project | B59: =Finance!$B$55 -> -0.005137086 | E59: Profit ÷ equity. Paid at sell-out; a for-sale condo has no annual cash yield.
A60: Levered IRR, all equity | B60: =Finance!$B$56 -> -0.0023193882 | E60: Annualized, from the monthly cash flow.
A61: Unlevered project IRR | B61: =Finance!$B$57 -> 0.059801144
A62: Investors (excluding sponsor): IRR | B62: =Finance!$B$60 -> -0.0023193882 | E62: After the pref and the sponsor's promote.
A63: Investors (excluding sponsor): equity multiple | B63: =Finance!$B$59 -> 0.99486291
A64: Sponsor promote | B64: =Finance!$B$61 -> 0
A65: Sponsor IRR on co-investment, with promote | B65: =Finance!$B$63 -> -0.0023193882
A67: BREAK-EVEN CONDO PRICE
A68: Average condo price for zero profit | B68: =(B19-B43/(1-'Rev & Unit-by-Unit'!$I$53-'Rev & Unit-by-Unit'!$I$54-'Rev & Unit-by-Unit'!$I$55-'Rev & Unit-by-Unit'!$I$60))/B8 -> 1316.2099 | E68: $ per sellable sf used for revenue, across all units. Approximate: holds the interest cost fixed while prices change.
A69: Average condo price for a 15% margin on cost | B69: =(B19+(0.15*B40-B43)/(1-'Rev & Unit-by-Unit'!$I$53-'Rev & Unit-by-Unit'!$I$54-'Rev & Unit-by-Unit'!$I$55-'Rev & Unit-by-Unit'!$I$60))/B8 -> 1616.3095 | E69: Same basis and approximation.
A71: Preliminary feasibility figures for discussion only; not an offer to sell securities.

Sheet Rev & Unit-by-Unit
A1: 246 South 2nd Street · Revenue and Unit-by-Unit
A2: Base (8 stories at 85 ft, 9 units). All sales revenue lives here: each unit's area and price, the commercial condo value, and the sale costs that take gross revenue down to net revenue. Finance and Master read from this sheet.
A3: Blue = input. Green = linked from Hard Costs. Black = formula. Yellow = the sellable-area adjustment, which affects revenue only.
A5: PRICING
A6: Price, standard units | G6: 1450 | H6: $ / sf | I6: Placeholder at 725 Grand's base case, $1,450/sf, until the Southside comps are pulled. The OM compares an upside at $1,650/sf.
A7: Mezzanine duplex premium (not used) | G7: 0.2 | H7: over standard | I7: No duplex or mezzanine units in this design.
A8: Price, mezzanine duplexes | G8: =$G$6*(1+$G$7) -> 1740 | H8: $ / sf
A10: SELLABLE-AREA ADJUSTMENT (revenue only)
A11: Design sellable sf, from the Hard Costs unit mix | G11: ='Hard Costs'!$C$10 -> 6879 | H11: sf | I11: The real area the costs, zoning check and 3D model use.
A12: Target sellable sf for revenue | G12: 0 | H12: sf | I12: Off (0): revenue uses the designed area. Enter a target to show an upside stretch.
A13: Adjustment | G13: =IF($G$12>0,$G$12-$G$11,0) -> 0 | H13: sf | I13: Spread pro rata across the units below. Does not change construction costs.
A14: Adjustment as a share of design area | G14: =$G$13/$G$11 -> 0
A16: UNIT-BY-UNIT
A17: Unit | B17: Floor(s) | C17: Type (from the unit mix) | D17: Bed-rooms | E17: Baths | F17: Mezza-nine | G17: Design sf (model) | H17: Adjust-ment sf | I17: Sellable sf | J17: Base $ / sf | K17: Unit premium / discount | L17: Asking price override ($) | M17: Unit price ($) | N17: Final $ / sf | O17: Closes, months after TCO | P17: Notes
A18: 4F | B18: 4 | C18: ='Hard Costs'!$B$29 -> Affordable 1-bedroom, floor 4 (4F), for sale | D18: 1 | E18: ='Hard Costs'!$G$29 -> 1 | F18: =IF('Hard Costs'!$H$29=1,"Yes","No") -> No | G18: 858 | H18: =G18*$G$14 -> 0 | I18: =G18+H18 -> 858 | J18: =IF('Hard Costs'!$H$29=1,$G$8,$G$6) -> 1450 | K18: 0 | L18: 300000 | M18: =IF(N(L18)>0,L18,I18*J18*(1+K18)) -> 300000 | N18: =M18/I18 -> 349.65035 | O18: 1 | P18: Affordable homeownership unit, priced at the affordable sale price, not market comps. Closes at TCO.
A19: 4R | B19: 4 | C19: ='Hard Costs'!$B$30 -> 1-bedroom, rear, floors 4-7 (4R, 5R, 6R, 7R) | D19: 1 | E19: ='Hard Costs'!$G$30 -> 1 | F19: =IF('Hard Costs'!$H$30=1,"Yes","No") -> No | G19: 714 | H19: =G19*$G$14 -> 0 | I19: =G19+H19 -> 714 | J19: =IF('Hard Costs'!$H$30=1,$G$8,$G$6) -> 1450 | K19: 0 | M19: =IF(N(L19)>0,L19,I19*J19*(1+K19)) -> 1035300 | N19: =M19/I19 -> 1450 | O19: 1 | P19: Rear, with an 81 sf balcony. Presold off the plans; closes at TCO.
A20: 5F | B20: 5 | C20: ='Hard Costs'!$B$31 -> 2-bedroom, street, floors 5-6 (5F, 6F) | D20: 2 | E20: ='Hard Costs'!$G$31 -> 2 | F20: =IF('Hard Costs'!$H$31=1,"Yes","No") -> No | G20: 858 | H20: =G20*$G$14 -> 0 | I20: =G20+H20 -> 858 | J20: =IF('Hard Costs'!$H$31=1,$G$8,$G$6) -> 1450 | K20: 0 | M20: =IF(N(L20)>0,L20,I20*J20*(1+K20)) -> 1244100 | N20: =M20/I20 -> 1450 | O20: 1 | P20: Street side. Presold off the plans; closes at TCO.
A21: 5R | B21: 5 | C21: ='Hard Costs'!$B$30 -> 1-bedroom, rear, floors 4-7 (4R, 5R, 6R, 7R) | D21: 1 | E21: ='Hard Costs'!$G$30 -> 1 | F21: =IF('Hard Costs'!$H$30=1,"Yes","No") -> No | G21: 719 | H21: =G21*$G$14 -> 0 | I21: =G21+H21 -> 719 | J21: =IF('Hard Costs'!$H$30=1,$G$8,$G$6) -> 1450 | K21: 0 | M21: =IF(N(L21)>0,L21,I21*J21*(1+K21)) -> 1042550 | N21: =M21/I21 -> 1450 | O21: 1 | P21: Rear, with an 85 sf balcony. Presold off the plans; closes at TCO.
A22: 6F | B22: 6 | C22: ='Hard Costs'!$B$31 -> 2-bedroom, street, floors 5-6 (5F, 6F) | D22: 2 | E22: ='Hard Costs'!$G$31 -> 2 | F22: =IF('Hard Costs'!$H$31=1,"Yes","No") -> No | G22: 858 | H22: =G22*$G$14 -> 0 | I22: =G22+H22 -> 858 | J22: =IF('Hard Costs'!$H$31=1,$G$8,$G$6) -> 1450 | K22: 0 | M22: =IF(N(L22)>0,L22,I22*J22*(1+K22)) -> 1244100 | N22: =M22/I22 -> 1450 | O22: 1 | P22: Street side. Presold off the plans; closes at TCO.
A23: 6R | B23: 6 | C23: ='Hard Costs'!$B$30 -> 1-bedroom, rear, floors 4-7 (4R, 5R, 6R, 7R) | D23: 1 | E23: ='Hard Costs'!$G$30 -> 1 | F23: =IF('Hard Costs'!$H$30=1,"Yes","No") -> No | G23: 719 | H23: =G23*$G$14 -> 0 | I23: =G23+H23 -> 719 | J23: =IF('Hard Costs'!$H$30=1,$G$8,$G$6) -> 1450 | K23: 0 | M23: =IF(N(L23)>0,L23,I23*J23*(1+K23)) -> 1042550 | N23: =M23/I23 -> 1450 | O23: 1 | P23: Rear, with a 55 sf balcony. Presold off the plans; closes at TCO.
A24: 7F | B24: 7 | C24: ='Hard Costs'!$B$32 -> Studio with street terrace, floor 7 (7F) | D24: 0 | E24: ='Hard Costs'!$G$32 -> 1 | F24: =IF('Hard Costs'!$H$32=1,"Yes","No") -> No | G24: 567 | H24: =G24*$G$14 -> 0 | I24: =G24+H24 -> 567 | J24: =IF('Hard Costs'!$H$32=1,$G$8,$G$6) -> 1450 | K24: 0 | M24: =IF(N(L24)>0,L24,I24*J24*(1+K24)) -> 822150 | N24: =M24/I24 -> 1450 | O24: 1 | P24: Studio with a 292 sf street terrace on the setback. Presold off the plans; closes at TCO.
A25: 7R | B25: 7 | C25: ='Hard Costs'!$B$30 -> 1-bedroom, rear, floors 4-7 (4R, 5R, 6R, 7R) | D25: 1 | E25: ='Hard Costs'!$G$30 -> 1 | F25: =IF('Hard Costs'!$H$30=1,"Yes","No") -> No | G25: 723 | H25: =G25*$G$14 -> 0 | I25: =G25+H25 -> 723 | J25: =IF('Hard Costs'!$H$30=1,$G$8,$G$6) -> 1450 | K25: 0 | M25: =IF(N(L25)>0,L25,I25*J25*(1+K25)) -> 1048350 | N25: =M25/I25 -> 1450 | O25: 1 | P25: Rear, with a 52 sf balcony. Presold off the plans; closes at TCO.
A26: PH | B26: 8 | C26: ='Hard Costs'!$B$33 -> Full-floor penthouse, floor 8, 2 bedrooms + private roof | D26: 2 | E26: ='Hard Costs'!$G$33 -> 2 | F26: =IF('Hard Costs'!$H$33=1,"Yes","No") -> No | G26: 863 | H26: =G26*$G$14 -> 0 | I26: =G26+H26 -> 863 | J26: =IF('Hard Costs'!$H$33=1,$G$8,$G$6) -> 1450 | K26: 0 | M26: =IF(N(L26)>0,L26,I26*J26*(1+K26)) -> 1251350 | N26: =M26/I26 -> 1450 | O26: 1 | P26: Full-floor penthouse: setback terrace and balcony (431 sf) plus a 1,505 sf private roof. Presold off the plans; closes at TCO.
A27: Total | D27: =SUM(D18:D26) -> 11 | E27: =SUM(E18:E26) -> 12 | G27: =SUM(G18:G26) -> 6879 | H27: =SUM(H18:H26) -> 0 | I27: =SUM(I18:I26) -> 6879 | M27: =SUM(M18:M26) -> 9030450 | N27: =M27/I27 -> 1312.7562 | O27: =MAX(O18:O26) -> 1
A28: Check against the Hard Costs unit mix | G28: =IF(AND(COUNT(G18:G26)='Hard Costs'!$C$12,ABS(G27-$G$11)<1),"OK","UNIT MIX CHANGED: update this list") -> OK | I28: If you change the unit mix on Hard Costs, add or remove rows here to match. Design sf per unit is typed in from the model.
A29: Revenue from the sellable-area adjustment | M29: =IF(N(L18)>0,0,H18*J18*(1+K18))+IF(N(L19)>0,0,H19*J19*(1+K19))+IF(N(L20)>0,0,H20*J20*(1+K20))+IF(N(L21)>0,0,H21*J21*(1+K21))+IF(N(L22)>0,0,H22*J22*(1+K22))+IF(N(L23)>0,0,H23*J23*(1+K23))+IF(N(L24)>0,0,H24*J24*(1+K24))+IF(N(L25)>0,0,H25*J25*(1+K25))+IF(N(L26)>0,0,H26*J26*(1+K26)) -> 0 | P29: Gross condo sales that come only from the adjustment (units with an asking-price override excluded).
A31: COMMERCIAL CONDO
A32: Commercial at grade (1st floor), sf | G32: ='Hard Costs'!$C$9 -> 1717 | H32: sf | I32: Sellable, from the model; set on Hard Costs.
A33: Rent, at grade | G33: 65 | H33: $ / sf / yr | I33: Placeholder for a mid-block Southside storefront (725 Grand used $90 for a Grand and Graham corner). Confirm with a broker.
A34: Commercial, 2nd floor, sf | G34: ='Hard Costs'!$C$22 -> 2616 | H34: sf | I34: Full 2nd floor: office, medical or community use. Set on Hard Costs.
A35: Rent, 2nd floor | G35: 40 | H35: $ / sf / yr | I35: Placeholder for second-floor space. Confirm with a broker.
A36: Vacancy | G36: 0 | I36: 0% as in the 725 Grand base case (pre-leased). The 5% value below is what a lender might use.
A37: Landlord expenses | G37: 0.03 | H37: of rent
A38: Cellar commercial and community facility area | G38: ='Hard Costs'!$C$17 -> 1857 | H38: sf | I38: Below-grade space sold with the commercial condo. Set on Hard Costs.
A39: Cellar rent | G39: 25 | H39: $ / sf / yr | I39: Below-grade space rents for a fraction of the ground floor.
A40: Net operating income | G40: =($G$32*$G$33+$G$34*$G$35+$G$38*$G$39)*(1-$G$36-$G$37) -> 254789.9 | H40: $ / yr | I40: Ground floor, 2nd floor and cellar, less vacancy and landlord expenses.
A41: Cap rate | G41: 0.05
A42: Commercial condo sale value | G42: =$G$40/$G$41 -> 5095798 | H42: $
A43: Value at 5% vacancy, for comparison | G43: =($G$32*$G$33+$G$34*$G$35+$G$38*$G$39)*(1-0.05-$G$37)/$G$41 -> 4833128 | H43: $ | I43: What a lender or appraiser might use instead.
A45: GROSS REVENUE
A46: Condo sales, gross (all units above) | G46: =$M$27 -> 9030450 | H46: $
A47: Commercial condo sale value | G47: =$G$42 -> 5095798 | H47: $
A48: Gross revenue | G48: =$G$46+$G$47 -> 14126248 | H48: $
A50: SALE COSTS
A51: Line item | G51: Basis | H51: Basis unit | I51: Rate | J51: Rate basis | M51: Total ($) | N51: % of gross | P51: Notes
A52: Condo unit sales
A53: Sales commissions (in-house sales plus co-brokers) | G53: =$M$27 -> 9030450 | H53: $ gross sales | I53: 0.03 | J53: % of sales | M53: =G53*I53 -> 270913.5 | N53: =M53/$G$48 -> 0.019178022 | P53: 725 Grand owner's rate, 3%: part of the sales in-house, some co-brokered.
A54: NYC Real Property Transfer Tax, paid by sponsor | G54: =$M$27 -> 9030450 | H54: $ gross sales | I54: 0.01425 | J54: % of sales | M54: =G54*I54 -> 128683.91 | N54: =M54/$G$48 -> 0.0091095606 | P54: Owner: the sponsor pays, as most sellers do. Rate for residential sales over $500,000.
A55: NYS transfer tax, paid by sponsor | G55: =$M$27 -> 9030450 | H55: $ gross sales | I55: 0.004 | J55: % of sales | M55: =G55*I55 -> 36121.8 | N55: =M55/$G$48 -> 0.0025570696 | P55: 0.4% under $3M per unit; 0.65% for a unit at $3M or more.
A56: Sponsor's closing attorney | G56: ='Hard Costs'!$C$12 -> 9 | H56: units | I56: 2500 | J56: $ / unit | M56: =G56*I56 -> 22500 | N56: =M56/$G$48 -> 0.0015927796
A57: Offering plan amendments (pricing, budget, closing) | G57: 1 | H57: allowance | I57: 25000 | J57: lump sum | M57: =G57*I57 -> 25000 | N57: =M57/$G$48 -> 0.0017697551
A58: Condo declaration, tax-lot apportionment and recording | G58: 1 | H58: allowance | I58: 35000 | J58: lump sum | M58: =G58*I58 -> 35000 | N58: =M58/$G$48 -> 0.0024776572 | P58: Needed before the first unit can close.
A59: Staging (no duplexes in this design) | G59: ='Hard Costs'!$H$34 -> 0 | H59: units | I59: 25000 | J59: $ / unit | M59: =G59*I59 -> 0 | N59: =M59/$G$48 -> 0 | P59: Set a count here to stage a model unit.
A60: Buyer closing credits and concessions | G60: =$M$27 -> 9030450 | H60: $ gross sales | I60: 0 | J60: % of sales | M60: =G60*I60 -> 0 | N60: =M60/$G$48 -> 0 | P60: Set if you plan to offer credits to move units.
A61: Condo sale costs | M61: =SUM(M53:M60) -> 518219.21 | N61: =M61/$G$48 -> 0.036684845
A63: Commercial condo sale
A64: Brokerage commission | G64: =$G$42 -> 5095798 | H64: $ sale value | I64: 0.06 | J64: % of sale | M64: =G64*I64 -> 305747.88 | N64: =M64/$G$48 -> 0.021643955
A65: NYC Real Property Transfer Tax | G65: =$G$42 -> 5095798 | H65: $ sale value | I65: 0.02625 | J65: % of sale | M65: =G65*I65 -> 133764.7 | N65: =M65/$G$48 -> 0.0094692304 | P65: Commercial rate for sales over $500,000.
A66: NYS transfer tax | G66: =$G$42 -> 5095798 | H66: $ sale value | I66: 0.0065 | J66: % of sale | M66: =G66*I66 -> 33122.687 | N66: =M66/$G$48 -> 0.0023447618 | P66: Commercial rate at $2M or more.
A67: Seller legal fees | G67: =$G$42 -> 5095798 | H67: $ sale value | I67: 0.005 | J67: % of sale | M67: =G67*I67 -> 25478.99 | N67: =M67/$G$48 -> 0.0018036629
A68: Commercial sale costs | M68: =SUM(M64:M67) -> 498114.25 | N68: =M68/$G$48 -> 0.03526161
A70: End-loan packages and lender releases
A71: Project approval package for buyers' mortgage lenders | G71: 1 | H71: allowance | I71: 15000 | J71: lump sum | M71: =G71*I71 -> 15000 | N71: =M71/$G$48 -> 0.0010618531 | P71: Condo questionnaires, budget and insurance certificates so buyers' banks will lend in the building. Owner: to be refined later.
A72: Construction lender partial-release fees | G72: ='Hard Costs'!$C$12 -> 9 | H72: units | I72: 1000 | J72: $ / unit | M72: =G72*I72 -> 9000 | N72: =M72/$G$48 -> 0.00063711185 | P72: Lender releases each unit from the construction mortgage at closing.
A73: Construction loan payoff and satisfaction recording | G73: 1 | H73: allowance | I73: 10000 | J73: lump sum | M73: =G73*I73 -> 10000 | N73: =M73/$G$48 -> 0.00070790206
A74: End-loan and release costs | M74: =SUM(M71:M73) -> 34000 | N74: =M74/$G$48 -> 0.002406867
A76: TOTAL SALE COSTS | M76: =M61+M68+M74 -> 1050333.5 | N76: =M76/$G$48 -> 0.074353322
A78: NET REVENUE | M78: =$G$48-M76 -> 13075915 | N78: =M78/$G$48 -> 0.92564668
A79: Gross revenue less all sale costs. Sponsor wind-down costs are on the Soft Costs sheet.
A81: WHAT THE OWNER ADJUSTMENTS ADD (net of sale costs)
A82: Sellable-area adjustment | M82: =$M$29*(1-$I$53-$I$54-$I$55-$I$60) -> 0 | P82: Off in this case (no target set above).
A83: Commercial at 0% vacancy, vs 5% | M83: =($G$42-$G$43)*(1-I64-I65-I66-I67) -> 236994.01 | P83: Commercial value above the comparison value, less commercial sale costs.

Sheet Finance
A1: 246 South 2nd Street · Finance
A2: 246 South 2nd Street on its own 3,100 sf lot in R6 with a commercial overlay: 8 stories at 85 ft (13'-11" ground floor, 11 ft 2nd floor, 10 ft above), plus a cellar and a private roof. 9 condos (8 market-rate and one affordable homeownership unit), 6,879 sellable sf; commercial on the 1st and 2nd floors (4,333 sf sellable) plus 1,857 sf in the cellar; Zone Green (ULEB) 5% exclusion; no air rights or certificates; all-electric.
A3: Blue = input you can change. Green = linked from the Hard Costs, Soft Costs and Rev & Unit-by-Unit sheets. Black = formula. The schedule months are placeholders until we set the timing together; the Gantt chart will use them.
A5: SCHEDULE (placeholder months)
A6: Pre-development: design, approvals and permits | B6: 6 | C6: months | D6: From land closing (month 0) to the start of construction. Equity carries these months.
A7: Construction: ground-breaking to TCO | B7: 20 | C7: months | D7: 20 months, as in the 725 Grand base case. Hard-cost draws come from the Gantt sheet.
A8: Sell-out after completion | B8: 6 | C8: months | D8: Window for closings after TCO. Each unit closes in the month set on the Rev & Unit-by-Unit sheet: presold units at TCO, the staged duplexes a few months later.
A9: Retail sale closes, months after completion | B9: 1 | C9: months
A10: Project length | B10: =$B$6+$B$7+$B$8 -> 32 | C10: months | D10: The Soft Costs sheet's project length links here. The monthly grid below runs 48 months.
A12: CONSTRUCTION LOAN
A13: Loan-to-cost | B13: 0.7 | D13: Share of costs before financing that the loan funds. Equity goes in first.
A14: Interest rate | B14: 0.095 | C14: per year | D14: Owner, Oct 16 2026: 9.5%. Accrues monthly on the drawn balance and is added to the loan.
A15: Origination fee | B15: 0.01 | C15: of commitment | D15: Paid when the loan closes, in the first month of construction.
A16: Interest reserve allowance | B16: 0.1 | C16: of loan | D16: Added to the loan commitment to cover capitalized interest. Sizes the commitment, the origination fee and the mortgage recording tax.
A18: EQUITY
A19: Preferred return to investors | B19: 0.08 | C19: per year | D19: Compounded monthly on invested capital until it is returned. The deck uses 8%; your Base w Fin tab charged 12% on land equity.
A20: Sponsor promote above the pref | B20: 0.3 | C20: of cash above pref | D20: After capital plus pref is paid back, the sponsor takes this share and investors the rest (the deck's 70/30).
A21: Sponsor co-investment | B21: 0.1 | C21: of equity | D21: Sponsor's own money in the deal, on the same terms as investors.
A22: Equity placement fee | B22: 0 | C22: of equity | D22: Fee to a broker for raising the equity, paid at closing. 0% unless you use a placement agent.
A24: FROM THE COST SHEETS
A25: Land purchase price | B25: ='Soft Costs'!$C$7 -> 4000000 | C25: $ | D25: Paid at closing, month 0.
A26: Inclusionary Housing certificates (none) | B26: ='Soft Costs'!$G$24 -> 0 | C26: $ | D26: Not needed for this design.
A27: Total hard cost | B27: ='Hard Costs'!$G$121 -> 6533100 | C27: $
A28: Construction soft costs, before mortgage recording tax | B28: ='Soft Costs'!$G$49 -> 1549116.8 | C28: $ | D28: Spread evenly from closing to the end of construction.
A29: Mortgage recording tax on the construction loan | B29: ='Soft Costs'!$G$51 -> 260492.59 | C29: $ | D29: Paid when the loan closes.
A30: Condo gross sales | B30: ='Rev & Unit-by-Unit'!$M$27 -> 9030450 | C30: $
A31: Condo sale costs | B31: ='Rev & Unit-by-Unit'!$M$61 -> 518219.21 | C31: $ | D31: Commissions, transfer taxes and closing costs, paid as units close.
A32: Retail condo sale value | B32: ='Rev & Unit-by-Unit'!$G$42 -> 5095798 | C32: $
A33: Retail sale costs | B33: ='Rev & Unit-by-Unit'!$M$68 -> 498114.25 | C33: $
A34: End-loan packages and sponsor wind-down | B34: ='Rev & Unit-by-Unit'!$M$74+'Soft Costs'!$G$59 -> 96665.5 | C34: $ | D34: Paid in the last month.
A36: LOAN AND EQUITY SIZING
A37: Costs before financing, excluding recording tax | B37: =$B$25+$B$26+$B$27+$B$28 -> 12082217 | C37: $ | D37: Land + hard + construction soft costs.
A38: Loan commitment | B38: =$B$13*$B$37*(1+$B$16) -> 9303306.9 | C38: $ | D38: Loan-to-cost × costs, plus the interest reserve allowance. The Soft Costs sheet's recording tax is figured on this.
A39: Loan origination fee | B39: =$B$15*$B$38 -> 93033.069 | C39: $
A40: Costs before the loan closes | B40: =$B$25+$B$26+$B$28*($B$6+1)/($B$6+$B$7+1) -> 4401622.9 | C40: $ | D40: Land and pre-development soft costs. Equity must cover at least this.
A41: Equity required | B41: =MAX((1-$B$13)*($B$37+$B$29),$B$40) -> 4401622.9 | C41: $ | D41: (1 - loan-to-cost) x costs including recording tax, or the costs before the loan closes if that is more.
A42: Equity placement fee | B42: =$B$22*$B$41 -> 0 | C42: $
A43: Total equity | B43: =$B$41+$B$42 -> 4401622.9 | C43: $ | D43: Invested first, before any loan draws.
A45: RESULTS
A46: Total project cost, including financing | B46: =B78+B82 -> 13035861 | C46: $
A47: of which construction loan interest | B47: =B82 -> 600118.08 | C47: $
A48: Peak loan balance | B48: =MAX(D93:AY93) -> 8634237.7 | C48: $ | D48: Highest drawn balance, including capitalized interest.
A49: Loan commitment less peak balance | B49: =$B$38-B48 -> 669069.26 | C49: $ | D49: Negative means the loan as sized would not cover the costs and interest: raise loan-to-cost or the interest reserve.
A50: Equity invested | B50: =B81 -> 4401622.9 | C50: $
A51: Net sale proceeds | B51: =B90 -> 13013249 | C51: $
A52: Profit | B52: =B99 -> -22611.515 | C52: $ | D52: Everything returned to equity less everything equity put in.
A53: Margin on cost | B53: =B52/B46 -> -0.0017345625
A54: Equity multiple | B54: =B98/B81 -> 0.99486291
A55: Cash-on-cash return, whole project | B55: =B52/B50 -> -0.005137086 | D55: Total cash returned above cash invested, as a share of the cash invested. A for-sale condo pays out at the end, so there is no annual cash yield.
A56: Levered IRR, all equity | B56: =IFERROR((1+IRR(D99:AY99))^12-1,"n/a") -> -0.0023193882 | C56: per year | D56: Annualized from the monthly equity cash flow.
A57: Unlevered project IRR | B57: =IFERROR((1+IRR(D112:AY112))^12-1,"n/a") -> 0.059801144 | C57: per year | D57: Land, hard and soft costs against net sale proceeds, with no loan.
A58: Investors (excluding sponsor): profit | B58: =B108 -> -20350.364 | C58: $
A59: Investors (excluding sponsor): equity multiple | B59: =(B108+B81*(1-$B$21))/(B81*(1-$B$21)) -> 0.99486291
A60: Investors (excluding sponsor): IRR | B60: =IFERROR((1+IRR(D108:AY108))^12-1,"n/a") -> -0.0023193882 | C60: per year
A61: Sponsor: promote | B61: =B106 -> 0 | C61: $
A62: Sponsor: promote plus co-investment profit | B62: =B109 -> -2261.1515 | C62: $
A63: Sponsor: IRR on co-investment | B63: =IFERROR((1+IRR(D109:AY109))^12-1,"n/a") -> -0.0023193882 | C63: per year | D63: On the sponsor's co-investment, with the promote included.
A64: Check: loan balance left at the end (should be 0) | B64: =AY95 -> 0 | C64: $
A66: MONTHLY CASH FLOW
A67: Month | B67: Total | D67: 0 | E67: 1 | F67: 2 | G67: 3 | H67: 4 | I67: 5 | J67: 6 | K67: 7 | L67: 8 | M67: 9 | N67: 10 | O67: 11 | P67: 12 | Q67: 13 | R67: 14 | S67: 15 | T67: 16 | U67: 17 | V67: 18 | W67: 19 | X67: 20 | Y67: 21 | Z67: 22 | AA67: 23 | AB67: 24 | AC67: 25 | AD67: 26 | AE67: 27 | AF67: 28 | AG67: 29 | AH67: 30 | AI67: 31 | AJ67: 32 | AK67: 33 | AL67: 34 | AM67: 35 | AN67: 36 | AO67: 37 | AP67: 38 | AQ67: 39 | AR67: 40 | AS67: 41 | AT67: 42 | AU67: 43 | AV67: 44 | AW67: 45 | AX67: 46 | AY67: 47
A68: Phase | D68: =IF(D$67=0,"Close",IF(D$67<=$B$6,"Pre-dev",IF(D$67<=$B$6+$B$7,"Build",IF(D$67<=$B$10,"Sell","")))) -> Close | E68: =IF(E$67=0,"Close",IF(E$67<=$B$6,"Pre-dev",IF(E$67<=$B$6+$B$7,"Build",IF(E$67<=$B$10,"Sell","")))) -> Pre-dev | F68: =IF(F$67=0,"Close",IF(F$67<=$B$6,"Pre-dev",IF(F$67<=$B$6+$B$7,"Build",IF(F$67<=$B$10,"Sell","")))) -> Pre-dev | G68: =IF(G$67=0,"Close",IF(G$67<=$B$6,"Pre-dev",IF(G$67<=$B$6+$B$7,"Build",IF(G$67<=$B$10,"Sell","")))) -> Pre-dev | H68: =IF(H$67=0,"Close",IF(H$67<=$B$6,"Pre-dev",IF(H$67<=$B$6+$B$7,"Build",IF(H$67<=$B$10,"Sell","")))) -> Pre-dev | I68: =IF(I$67=0,"Close",IF(I$67<=$B$6,"Pre-dev",IF(I$67<=$B$6+$B$7,"Build",IF(I$67<=$B$10,"Sell","")))) -> Pre-dev | J68: =IF(J$67=0,"Close",IF(J$67<=$B$6,"Pre-dev",IF(J$67<=$B$6+$B$7,"Build",IF(J$67<=$B$10,"Sell","")))) -> Pre-dev | K68: =IF(K$67=0,"Close",IF(K$67<=$B$6,"Pre-dev",IF(K$67<=$B$6+$B$7,"Build",IF(K$67<=$B$10,"Sell","")))) -> Build | ... AY68: =IF(AY$67=0,"Close",IF(AY$67<=$B$6,"Pre-dev",IF(AY$67<=$B$6+$B$7,"Build",IF(AY$67<=$B$10,"Sell",""))))
A70: Costs
A71: Land | B71: =SUM(D71:AY71) -> 4000000 | D71: =IF(D$67=0,$B$25,0) -> 4000000 | E71: =IF(E$67=0,$B$25,0) -> 0 | F71: =IF(F$67=0,$B$25,0) -> 0 | G71: =IF(G$67=0,$B$25,0) -> 0 | H71: =IF(H$67=0,$B$25,0) -> 0 | I71: =IF(I$67=0,$B$25,0) -> 0 | J71: =IF(J$67=0,$B$25,0) -> 0 | K71: =IF(K$67=0,$B$25,0) -> 0 | ... AY71: =IF(AY$67=0,$B$25,0) -> 0
A72: IH certificates | B72: =SUM(D72:AY72) -> 0 | D72: =IF(D$67=$B$6,$B$26,0) -> 0 | E72: =IF(E$67=$B$6,$B$26,0) -> 0 | F72: =IF(F$67=$B$6,$B$26,0) -> 0 | G72: =IF(G$67=$B$6,$B$26,0) -> 0 | H72: =IF(H$67=$B$6,$B$26,0) -> 0 | I72: =IF(I$67=$B$6,$B$26,0) -> 0 | J72: =IF(J$67=$B$6,$B$26,0) -> 0 | K72: =IF(K$67=$B$6,$B$26,0) -> 0 | ... AY72: =IF(AY$67=$B$6,$B$26,0) -> 0
A73: Hard costs (from the Gantt draw schedule) | B73: =SUM(D73:AY73) -> 6533100 | D73: =Gantt!L79 -> 0 | E73: =Gantt!M79 -> 0 | F73: =Gantt!N79 -> 0 | G73: =Gantt!O79 -> 0 | H73: =Gantt!P79 -> 0 | I73: =Gantt!Q79 -> 0 | J73: =Gantt!R79 -> 0 | K73: =Gantt!S79 -> 29695.909 | ... AY73: =Gantt!BG79 -> 0
A74: Soft costs, before recording tax | B74: =SUM(D74:AY74) -> 1549116.8 | D74: =IF(D$67<=$B$6+$B$7,$B$28/($B$6+$B$7+1),0) -> 57374.696 | E74: =IF(E$67<=$B$6+$B$7,$B$28/($B$6+$B$7+1),0) -> 57374.696 | F74: =IF(F$67<=$B$6+$B$7,$B$28/($B$6+$B$7+1),0) -> 57374.696 | G74: =IF(G$67<=$B$6+$B$7,$B$28/($B$6+$B$7+1),0) -> 57374.696 | H74: =IF(H$67<=$B$6+$B$7,$B$28/($B$6+$B$7+1),0) -> 57374.696 | I74: =IF(I$67<=$B$6+$B$7,$B$28/($B$6+$B$7+1),0) -> 57374.696 | J74: =IF(J$67<=$B$6+$B$7,$B$28/($B$6+$B$7+1),0) -> 57374.696 | K74: =IF(K$67<=$B$6+$B$7,$B$28/($B$6+$B$7+1),0) -> 57374.696 | ... AY74: =IF(AY$67<=$B$6+$B$7,$B$28/($B$6+$B$7+1),0) -> 0
A75: Mortgage recording tax | B75: =SUM(D75:AY75) -> 260492.59 | D75: =IF(D$67=$B$6+1,$B$29,0) -> 0 | E75: =IF(E$67=$B$6+1,$B$29,0) -> 0 | F75: =IF(F$67=$B$6+1,$B$29,0) -> 0 | G75: =IF(G$67=$B$6+1,$B$29,0) -> 0 | H75: =IF(H$67=$B$6+1,$B$29,0) -> 0 | I75: =IF(I$67=$B$6+1,$B$29,0) -> 0 | J75: =IF(J$67=$B$6+1,$B$29,0) -> 0 | K75: =IF(K$67=$B$6+1,$B$29,0) -> 260492.59 | ... AY75: =IF(AY$67=$B$6+1,$B$29,0) -> 0
A76: Loan origination fee | B76: =SUM(D76:AY76) -> 93033.069 | D76: =IF(D$67=$B$6+1,$B$39,0) -> 0 | E76: =IF(E$67=$B$6+1,$B$39,0) -> 0 | F76: =IF(F$67=$B$6+1,$B$39,0) -> 0 | G76: =IF(G$67=$B$6+1,$B$39,0) -> 0 | H76: =IF(H$67=$B$6+1,$B$39,0) -> 0 | I76: =IF(I$67=$B$6+1,$B$39,0) -> 0 | J76: =IF(J$67=$B$6+1,$B$39,0) -> 0 | K76: =IF(K$67=$B$6+1,$B$39,0) -> 93033.069 | ... AY76: =IF(AY$67=$B$6+1,$B$39,0) -> 0
A77: Equity placement fee | B77: =SUM(D77:AY77) -> 0 | D77: =IF(D$67=0,$B$42,0) -> 0 | E77: =IF(E$67=0,$B$42,0) -> 0 | F77: =IF(F$67=0,$B$42,0) -> 0 | G77: =IF(G$67=0,$B$42,0) -> 0 | H77: =IF(H$67=0,$B$42,0) -> 0 | I77: =IF(I$67=0,$B$42,0) -> 0 | J77: =IF(J$67=0,$B$42,0) -> 0 | K77: =IF(K$67=0,$B$42,0) -> 0 | ... AY77: =IF(AY$67=0,$B$42,0) -> 0
A78: Costs before interest | B78: =SUM(D78:AY78) -> 12435742 | D78: =SUM(D71:D77) -> 4057374.7 | E78: =SUM(E71:E77) -> 57374.696 | F78: =SUM(F71:F77) -> 57374.696 | G78: =SUM(G71:G77) -> 57374.696 | H78: =SUM(H71:H77) -> 57374.696 | I78: =SUM(I71:I77) -> 57374.696 | J78: =SUM(J71:J77) -> 57374.696 | K78: =SUM(K71:K77) -> 440596.27 | ... AY78: =SUM(AY71:AY77) -> 0
A80: Funding
A81: Equity in | B81: =SUM(D81:AY81) -> 4401622.9 | D81: =MIN(D78,$B$43-SUM($C81:C81)) -> 4057374.7 | E81: =MIN(E78,$B$43-SUM($C81:D81)) -> 57374.696 | F81: =MIN(F78,$B$43-SUM($C81:E81)) -> 57374.696 | G81: =MIN(G78,$B$43-SUM($C81:F81)) -> 57374.696 | H81: =MIN(H78,$B$43-SUM($C81:G81)) -> 57374.696 | I81: =MIN(I78,$B$43-SUM($C81:H81)) -> 57374.696 | J81: =MIN(J78,$B$43-SUM($C81:I81)) -> 57374.696 | K81: =MIN(K78,$B$43-SUM($C81:J81)) -> 1.8626451e-09 | ... AY81: =MIN(AY78,$B$43-SUM($C81:AX81)) -> 0
A82: Loan interest (added to the loan) | B82: =SUM(D82:AY82) -> 600118.08 | D82: =N(C95)*$B$14/12 -> 0 | E82: =N(D95)*$B$14/12 -> 0 | F82: =N(E95)*$B$14/12 -> 0 | G82: =N(F95)*$B$14/12 -> 0 | H82: =N(G95)*$B$14/12 -> 0 | I82: =N(H95)*$B$14/12 -> 0 | J82: =N(I95)*$B$14/12 -> 0 | K82: =N(J95)*$B$14/12 -> 0 | ... AY82: =N(AX95)*$B$14/12 -> 0
A83: Loan draw | B83: =SUM(D83:AY83) -> 8634237.7 | D83: =D78-D81+D82 -> 0 | E83: =E78-E81+E82 -> 0 | F83: =F78-F81+F82 -> 0 | G83: =G78-G81+G82 -> 0 | H83: =H78-H81+H82 -> 0 | I83: =I78-I81+I82 -> 0 | J83: =J78-J81+J82 -> 0 | K83: =K78-K81+K82 -> 440596.27 | ... AY83: =AY78-AY81+AY82 -> 0
A85: Sales
A86: Condo sales, gross (each unit in its closing month) | B86: =SUM(D86:AY86) -> 9030450 | D86: =SUMPRODUCT(--('Rev & Unit-by-Unit'!$O$18:$O$26+$B$6+$B$7=D$67),'Rev & Unit-by-Unit'!$M$18:$M$26) -> 0 | E86: =SUMPRODUCT(--('Rev & Unit-by-Unit'!$O$18:$O$26+$B$6+$B$7=E$67),'Rev & Unit-by-Unit'!$M$18:$M$26) -> 0 | F86: =SUMPRODUCT(--('Rev & Unit-by-Unit'!$O$18:$O$26+$B$6+$B$7=F$67),'Rev & Unit-by-Unit'!$M$18:$M$26) -> 0 | G86: =SUMPRODUCT(--('Rev & Unit-by-Unit'!$O$18:$O$26+$B$6+$B$7=G$67),'Rev & Unit-by-Unit'!$M$18:$M$26) -> 0 | H86: =SUMPRODUCT(--('Rev & Unit-by-Unit'!$O$18:$O$26+$B$6+$B$7=H$67),'Rev & Unit-by-Unit'!$M$18:$M$26) -> 0 | I86: =SUMPRODUCT(--('Rev & Unit-by-Unit'!$O$18:$O$26+$B$6+$B$7=I$67),'Rev & Unit-by-Unit'!$M$18:$M$26) -> 0 | J86: =SUMPRODUCT(--('Rev & Unit-by-Unit'!$O$18:$O$26+$B$6+$B$7=J$67),'Rev & Unit-by-Unit'!$M$18:$M$26) -> 0 | K86: =SUMPRODUCT(--('Rev & Unit-by-Unit'!$O$18:$O$26+$B$6+$B$7=K$67),'Rev & Unit-by-Unit'!$M$18:$M$26) -> 0 | ... AY86: =SUMPRODUCT(--('Rev & Unit-by-Unit'!$O$18:$O$26+$B$6+$B$7=AY$67),'Rev & Unit-by-Unit'!$M$18:$M$26) -> 0
A87: Condo sale costs, with each closing | B87: =SUM(D87:AY87) -> -518219.21 | D87: =-$B$31*D86/$B$30 -> 0 | E87: =-$B$31*E86/$B$30 -> 0 | F87: =-$B$31*F86/$B$30 -> 0 | G87: =-$B$31*G86/$B$30 -> 0 | H87: =-$B$31*H86/$B$30 -> 0 | I87: =-$B$31*I86/$B$30 -> 0 | J87: =-$B$31*J86/$B$30 -> 0 | K87: =-$B$31*K86/$B$30 -> 0 | ... AY87: =-$B$31*AY86/$B$30 -> 0
A88: Retail sale, net of sale costs | B88: =SUM(D88:AY88) -> 4597683.7 | D88: =IF(D$67=$B$6+$B$7+$B$9,$B$32-$B$33,0) -> 0 | E88: =IF(E$67=$B$6+$B$7+$B$9,$B$32-$B$33,0) -> 0 | F88: =IF(F$67=$B$6+$B$7+$B$9,$B$32-$B$33,0) -> 0 | G88: =IF(G$67=$B$6+$B$7+$B$9,$B$32-$B$33,0) -> 0 | H88: =IF(H$67=$B$6+$B$7+$B$9,$B$32-$B$33,0) -> 0 | I88: =IF(I$67=$B$6+$B$7+$B$9,$B$32-$B$33,0) -> 0 | J88: =IF(J$67=$B$6+$B$7+$B$9,$B$32-$B$33,0) -> 0 | K88: =IF(K$67=$B$6+$B$7+$B$9,$B$32-$B$33,0) -> 0 | ... AY88: =IF(AY$67=$B$6+$B$7+$B$9,$B$32-$B$33,0) -> 0
A89: End-loan and wind-down costs | B89: =SUM(D89:AY89) -> -96665.5 | D89: =-IF(D$67=$B$10,$B$34,0) -> 0 | E89: =-IF(E$67=$B$10,$B$34,0) -> 0 | F89: =-IF(F$67=$B$10,$B$34,0) -> 0 | G89: =-IF(G$67=$B$10,$B$34,0) -> 0 | H89: =-IF(H$67=$B$10,$B$34,0) -> 0 | I89: =-IF(I$67=$B$10,$B$34,0) -> 0 | J89: =-IF(J$67=$B$10,$B$34,0) -> 0 | K89: =-IF(K$67=$B$10,$B$34,0) -> 0 | ... AY89: =-IF(AY$67=$B$10,$B$34,0) -> 0
A90: Net sale proceeds | B90: =SUM(D90:AY90) -> 13013249 | D90: =SUM(D86:D89) -> 0 | E90: =SUM(E86:E89) -> 0 | F90: =SUM(F86:F89) -> 0 | G90: =SUM(G86:G89) -> 0 | H90: =SUM(H86:H89) -> 0 | I90: =SUM(I86:I89) -> 0 | J90: =SUM(J86:J89) -> 0 | K90: =SUM(K86:K89) -> 0 | ... AY90: =SUM(AY86:AY89) -> 0
A92: Construction loan
A93: Balance before repayment | D93: =N(C95)+D83 -> 0 | E93: =N(D95)+E83 -> 0 | F93: =N(E95)+F83 -> 0 | G93: =N(F95)+G83 -> 0 | H93: =N(G95)+H83 -> 0 | I93: =N(H95)+I83 -> 0 | J93: =N(I95)+J83 -> 0 | K93: =N(J95)+K83 -> 440596.27 | ... AY93: =N(AX95)+AY83 -> 0
A94: Repayment from sales | B94: =SUM(D94:AY94) -> 8634237.7 | D94: =MIN(MAX(D90,0),D93) -> 0 | E94: =MIN(MAX(E90,0),E93) -> 0 | F94: =MIN(MAX(F90,0),F93) -> 0 | G94: =MIN(MAX(G90,0),G93) -> 0 | H94: =MIN(MAX(H90,0),H93) -> 0 | I94: =MIN(MAX(I90,0),I93) -> 0 | J94: =MIN(MAX(J90,0),J93) -> 0 | K94: =MIN(MAX(K90,0),K93) -> 0 | ... AY94: =MIN(MAX(AY90,0),AY93) -> 0
A95: Closing balance | D95: =D93-D94 -> 0 | E95: =E93-E94 -> 0 | F95: =F93-F94 -> 0 | G95: =G93-G94 -> 0 | H95: =H93-H94 -> 0 | I95: =I93-I94 -> 0 | J95: =J93-J94 -> 0 | K95: =K93-K94 -> 440596.27 | ... AY95: =AY93-AY94 -> 0
A97: Equity
A98: Cash to equity after loan repayment | B98: =SUM(D98:AY98) -> 4379011.4 | D98: =D90-D94 -> 0 | E98: =E90-E94 -> 0 | F98: =F90-F94 -> 0 | G98: =G90-G94 -> 0 | H98: =H90-H94 -> 0 | I98: =I90-I94 -> 0 | J98: =J90-J94 -> 0 | K98: =K90-K94 -> 0 | ... AY98: =AY90-AY94 -> 0
A99: Net equity cash flow | B99: =SUM(D99:AY99) -> -22611.515 | D99: =D98-D81 -> -4057374.7 | E99: =E98-E81 -> -57374.696 | F99: =F98-F81 -> -57374.696 | G99: =G98-G81 -> -57374.696 | H99: =H98-H81 -> -57374.696 | I99: =I98-I81 -> -57374.696 | J99: =J98-J81 -> -57374.696 | K99: =K98-K81 -> -1.8626451e-09 | ... AY99: =AY98-AY81 -> 0
A101: Investor waterfall
A102: Owed to investors: capital plus pref | D102: =N(C104)*(1+$B$19)^(1/12)+D81 -> 4057374.7 | E102: =N(D104)*(1+$B$19)^(1/12)+E81 -> 4140854.7 | F102: =N(E104)*(1+$B$19)^(1/12)+F81 -> 4224871.7 | G102: =N(F104)*(1+$B$19)^(1/12)+G81 -> 4309429.4 | H102: =N(G104)*(1+$B$19)^(1/12)+H81 -> 4394531.1 | I102: =N(H104)*(1+$B$19)^(1/12)+I81 -> 4480180.3 | J102: =N(I104)*(1+$B$19)^(1/12)+J81 -> 4566380.6 | K102: =N(J104)*(1+$B$19)^(1/12)+K81 -> 4595760.9 | ... AY102: =N(AX104)*(1+$B$19)^(1/12)+AY81 -> 851564.8
A103: Paid toward capital plus pref | B103: =SUM(D103:AY103) -> 4475676.9 | D103: =MIN(MAX(D98,0),D102) -> 0 | E103: =MIN(MAX(E98,0),E102) -> 0 | F103: =MIN(MAX(F98,0),F102) -> 0 | G103: =MIN(MAX(G98,0),G102) -> 0 | H103: =MIN(MAX(H98,0),H102) -> 0 | I103: =MIN(MAX(I98,0),I102) -> 0 | J103: =MIN(MAX(J98,0),J102) -> 0 | K103: =MIN(MAX(K98,0),K102) -> 0 | ... AY103: =MIN(MAX(AY98,0),AY102) -> 0
A104: Still owed after payment | D104: =D102-D103 -> 4057374.7 | E104: =E102-E103 -> 4140854.7 | F104: =F102-F103 -> 4224871.7 | G104: =G102-G103 -> 4309429.4 | H104: =H102-H103 -> 4394531.1 | I104: =I102-I103 -> 4480180.3 | J104: =J102-J103 -> 4566380.6 | K104: =K102-K103 -> 4595760.9 | ... AY104: =AY102-AY103 -> 851564.8
A105: Cash above capital plus pref | B105: =SUM(D105:AY105) -> 0 | D105: =MAX(D98,0)-D103 -> 0 | E105: =MAX(E98,0)-E103 -> 0 | F105: =MAX(F98,0)-F103 -> 0 | G105: =MAX(G98,0)-G103 -> 0 | H105: =MAX(H98,0)-H103 -> 0 | I105: =MAX(I98,0)-I103 -> 0 | J105: =MAX(J98,0)-J103 -> 0 | K105: =MAX(K98,0)-K103 -> 0 | ... AY105: =MAX(AY98,0)-AY103 -> 0
A106: Sponsor promote | B106: =SUM(D106:AY106) -> 0 | D106: =D105*$B$20 -> 0 | E106: =E105*$B$20 -> 0 | F106: =F105*$B$20 -> 0 | G106: =G105*$B$20 -> 0 | H106: =H105*$B$20 -> 0 | I106: =I105*$B$20 -> 0 | J106: =J105*$B$20 -> 0 | K106: =K105*$B$20 -> 0 | ... AY106: =AY105*$B$20 -> 0
A107: Investors' cash flow (all equity) | B107: =SUM(D107:AY107) -> -22611.515 | D107: =D103+D105-D106+MIN(D98,0)-D81 -> -4057374.7 | E107: =E103+E105-E106+MIN(E98,0)-E81 -> -57374.696 | F107: =F103+F105-F106+MIN(F98,0)-F81 -> -57374.696 | G107: =G103+G105-G106+MIN(G98,0)-G81 -> -57374.696 | H107: =H103+H105-H106+MIN(H98,0)-H81 -> -57374.696 | I107: =I103+I105-I106+MIN(I98,0)-I81 -> -57374.696 | J107: =J103+J105-J106+MIN(J98,0)-J81 -> -57374.696 | K107: =K103+K105-K106+MIN(K98,0)-K81 -> -1.8626451e-09 | ... AY107: =AY103+AY105-AY106+MIN(AY98,0)-AY81 -> 0
A108: Investors excluding sponsor | B108: =SUM(D108:AY108) -> -20350.364 | D108: =D107*(1-$B$21) -> -3651637.2 | E108: =E107*(1-$B$21) -> -51637.227 | F108: =F107*(1-$B$21) -> -51637.227 | G108: =G107*(1-$B$21) -> -51637.227 | H108: =H107*(1-$B$21) -> -51637.227 | I108: =I107*(1-$B$21) -> -51637.227 | J108: =J107*(1-$B$21) -> -51637.227 | K108: =K107*(1-$B$21) -> -1.6763806e-09 | ... AY108: =AY107*(1-$B$21) -> 0
A109: Sponsor: co-investment plus promote | B109: =SUM(D109:AY109) -> -2261.1515 | D109: =D107*$B$21+D106 -> -405737.47 | E109: =E107*$B$21+E106 -> -5737.4696 | F109: =F107*$B$21+F106 -> -5737.4696 | G109: =G107*$B$21+G106 -> -5737.4696 | H109: =H107*$B$21+H106 -> -5737.4696 | I109: =I107*$B$21+I106 -> -5737.4696 | J109: =J107*$B$21+J106 -> -5737.4696 | K109: =K107*$B$21+K106 -> -1.8626451e-10 | ... AY109: =AY107*$B$21+AY106 -> 0
A111: Unlevered
A112: Project cash flow before financing | B112: =SUM(D112:AY112) -> 931032.23 | D112: =D90-D71-D72-D73-D74 -> -4057374.7 | E112: =E90-E71-E72-E73-E74 -> -57374.696 | F112: =F90-F71-F72-F73-F74 -> -57374.696 | G112: =G90-G71-G72-G73-G74 -> -57374.696 | H112: =H90-H71-H72-H73-H74 -> -57374.696 | I112: =I90-I71-I72-I73-I74 -> -57374.696 | J112: =J90-J71-J72-J73-J74 -> -57374.696 | K112: =K90-K71-K72-K73-K74 -> -87070.605 | ... AY112: =AY90-AY71-AY72-AY73-AY74 -> 0

Sheet Gantt
A1: 246 South 2nd Street · Gantt and Construction Draw Schedule
A2: Base (8 stories at 85 ft, 20-month build). Month by month from the equity raise to the last closing. Each hard-cost line is spread evenly between its start and end month; the owner-budget adjustment and contingency are spread pro rata.
A3: Blue = start and end months you can change. Green = linked. Shaded cells show when each activity happens; construction cells show the monthly draw in $ thousands.
A5: SCHEDULE
A6: Land closing (month 0) | B6: 46478 | F6: Placeholder carried from 725 Grand: 3 months to find investors, 3 months to close.
A7: Pre-development | B7: =Finance!$B$6 -> 6 | C7: months | F7: Set on the Finance sheet.
A8: Construction | B8: =Finance!$B$7 -> 20 | C8: months | F8: Set on the Finance sheet. Construction month 1 = project month pre-development + 1.
A9: Sell-out after TCO | B9: =Finance!$B$8 -> 6 | C9: months
A10: Offering plan accepted by the Attorney General | B10: 12 | C10: proj. month | F10: Presales start here. Contracts cannot be signed before acceptance.
A12: Project month | F12: -6 | G12: -5 | H12: -4 | I12: -3 | J12: -2 | K12: -1 | L12: 0 | M12: 1 | N12: 2 | O12: 3 | P12: 4 | Q12: 5 | R12: 6 | S12: 7 | T12: 8 | U12: 9 | V12: 10 | W12: 11 | X12: 12 | Y12: 13 | Z12: 14 | AA12: 15 | AB12: 16 | AC12: 17 | AD12: 18 | AE12: 19 | AF12: 20 | AG12: 21 | AH12: 22 | AI12: 23 | AJ12: 24 | AK12: 25 | AL12: 26 | AM12: 27 | AN12: 28 | AO12: 29 | AP12: 30 | AQ12: 31 | AR12: 32 | AS12: 33 | AT12: 34 | AU12: 35 | AV12: 36 | AW12: 37 | AX12: 38 | AY12: 39 | AZ12: 40 | BA12: 41 | BB12: 42 | BC12: 43 | BD12: 44 | BE12: 45 | BF12: 46 | BG12: 47
A13: Month | B13: Budget | C13: Start | D13: End | F13: =DATE(YEAR($B$6),MONTH($B$6)+F$12,1) -> 46296 | G13: =DATE(YEAR($B$6),MONTH($B$6)+G$12,1) -> 46327 | H13: =DATE(YEAR($B$6),MONTH($B$6)+H$12,1) -> 46357 | I13: =DATE(YEAR($B$6),MONTH($B$6)+I$12,1) -> 46388 | J13: =DATE(YEAR($B$6),MONTH($B$6)+J$12,1) -> 46419 | K13: =DATE(YEAR($B$6),MONTH($B$6)+K$12,1) -> 46447 | L13: =DATE(YEAR($B$6),MONTH($B$6)+L$12,1) -> 46478 | M13: =DATE(YEAR($B$6),MONTH($B$6)+M$12,1) -> 46508 | ... BG13: =DATE(YEAR($B$6),MONTH($B$6)+BG$12,1) -> 47908
A14: Phase | F14: =IF(F$12<0,"Raise",IF(F$12=0,"Close",IF(F$12<=$B$7,"Pre-dev",IF(F$12<=$B$7+$B$8,"Build",IF(F$12<=$B$7+$B$8+$B$9,"Sell",""))))) -> Raise | G14: =IF(G$12<0,"Raise",IF(G$12=0,"Close",IF(G$12<=$B$7,"Pre-dev",IF(G$12<=$B$7+$B$8,"Build",IF(G$12<=$B$7+$B$8+$B$9,"Sell",""))))) -> Raise | H14: =IF(H$12<0,"Raise",IF(H$12=0,"Close",IF(H$12<=$B$7,"Pre-dev",IF(H$12<=$B$7+$B$8,"Build",IF(H$12<=$B$7+$B$8+$B$9,"Sell",""))))) -> Raise | I14: =IF(I$12<0,"Raise",IF(I$12=0,"Close",IF(I$12<=$B$7,"Pre-dev",IF(I$12<=$B$7+$B$8,"Build",IF(I$12<=$B$7+$B$8+$B$9,"Sell",""))))) -> Raise | J14: =IF(J$12<0,"Raise",IF(J$12=0,"Close",IF(J$12<=$B$7,"Pre-dev",IF(J$12<=$B$7+$B$8,"Build",IF(J$12<=$B$7+$B$8+$B$9,"Sell",""))))) -> Raise | K14: =IF(K$12<0,"Raise",IF(K$12=0,"Close",IF(K$12<=$B$7,"Pre-dev",IF(K$12<=$B$7+$B$8,"Build",IF(K$12<=$B$7+$B$8+$B$9,"Sell",""))))) -> Raise | L14: =IF(L$12<0,"Raise",IF(L$12=0,"Close",IF(L$12<=$B$7,"Pre-dev",IF(L$12<=$B$7+$B$8,"Build",IF(L$12<=$B$7+$B$8+$B$9,"Sell",""))))) -> Close | M14: =IF(M$12<0,"Raise",IF(M$12=0,"Close",IF(M$12<=$B$7,"Pre-dev",IF(M$12<=$B$7+$B$8,"Build",IF(M$12<=$B$7+$B$8+$B$9,"Sell",""))))) -> Pre-dev | ... BG14: =IF(BG$12<0,"Raise",IF(BG$12=0,"Close",IF(BG$12<=$B$7,"Pre-dev",IF(BG$12<=$B$7+$B$8,"Build",IF(BG$12<=$B$7+$B$8+$B$9,"Sell","")))))
A16: BEFORE CONSTRUCTION | F16: Start and end are project months (0 = land closing).
A17: Equity raise: find investors | C17: -6 | D17: -4 | F17: =IF(AND(F$12>=$C17,F$12<=$D17),1,0) -> 1 | G17: =IF(AND(G$12>=$C17,G$12<=$D17),1,0) -> 1 | H17: =IF(AND(H$12>=$C17,H$12<=$D17),1,0) -> 1 | I17: =IF(AND(I$12>=$C17,I$12<=$D17),1,0) -> 0 | J17: =IF(AND(J$12>=$C17,J$12<=$D17),1,0) -> 0 | K17: =IF(AND(K$12>=$C17,K$12<=$D17),1,0) -> 0 | L17: =IF(AND(L$12>=$C17,L$12<=$D17),1,0) -> 0 | M17: =IF(AND(M$12>=$C17,M$12<=$D17),1,0) -> 0 | ... BG17: =IF(AND(BG$12>=$C17,BG$12<=$D17),1,0) -> 0
A18: Closing period | C18: -3 | D18: -1 | F18: =IF(AND(F$12>=$C18,F$12<=$D18),1,0) -> 0 | G18: =IF(AND(G$12>=$C18,G$12<=$D18),1,0) -> 0 | H18: =IF(AND(H$12>=$C18,H$12<=$D18),1,0) -> 0 | I18: =IF(AND(I$12>=$C18,I$12<=$D18),1,0) -> 1 | J18: =IF(AND(J$12>=$C18,J$12<=$D18),1,0) -> 1 | K18: =IF(AND(K$12>=$C18,K$12<=$D18),1,0) -> 1 | L18: =IF(AND(L$12>=$C18,L$12<=$D18),1,0) -> 0 | M18: =IF(AND(M$12>=$C18,M$12<=$D18),1,0) -> 0 | ... BG18: =IF(AND(BG$12>=$C18,BG$12<=$D18),1,0) -> 0
A19: Land closing | C19: 0 | D19: 0 | F19: =IF(AND(F$12>=$C19,F$12<=$D19),1,0) -> 0 | G19: =IF(AND(G$12>=$C19,G$12<=$D19),1,0) -> 0 | H19: =IF(AND(H$12>=$C19,H$12<=$D19),1,0) -> 0 | I19: =IF(AND(I$12>=$C19,I$12<=$D19),1,0) -> 0 | J19: =IF(AND(J$12>=$C19,J$12<=$D19),1,0) -> 0 | K19: =IF(AND(K$12>=$C19,K$12<=$D19),1,0) -> 0 | L19: =IF(AND(L$12>=$C19,L$12<=$D19),1,0) -> 1 | M19: =IF(AND(M$12>=$C19,M$12<=$D19),1,0) -> 0 | ... BG19: =IF(AND(BG$12>=$C19,BG$12<=$D19),1,0) -> 0
A20: Design and Buildings Department filing | C20: 1 | D20: 3 | F20: =IF(AND(F$12>=$C20,F$12<=$D20),1,0) -> 0 | G20: =IF(AND(G$12>=$C20,G$12<=$D20),1,0) -> 0 | H20: =IF(AND(H$12>=$C20,H$12<=$D20),1,0) -> 0 | I20: =IF(AND(I$12>=$C20,I$12<=$D20),1,0) -> 0 | J20: =IF(AND(J$12>=$C20,J$12<=$D20),1,0) -> 0 | K20: =IF(AND(K$12>=$C20,K$12<=$D20),1,0) -> 0 | L20: =IF(AND(L$12>=$C20,L$12<=$D20),1,0) -> 0 | M20: =IF(AND(M$12>=$C20,M$12<=$D20),1,0) -> 1 | ... BG20: =IF(AND(BG$12>=$C20,BG$12<=$D20),1,0) -> 0
A21: Phase I environmental | C21: 1 | D21: 4 | F21: =IF(AND(F$12>=$C21,F$12<=$D21),1,0) -> 0 | G21: =IF(AND(G$12>=$C21,G$12<=$D21),1,0) -> 0 | H21: =IF(AND(H$12>=$C21,H$12<=$D21),1,0) -> 0 | I21: =IF(AND(I$12>=$C21,I$12<=$D21),1,0) -> 0 | J21: =IF(AND(J$12>=$C21,J$12<=$D21),1,0) -> 0 | K21: =IF(AND(K$12>=$C21,K$12<=$D21),1,0) -> 0 | L21: =IF(AND(L$12>=$C21,L$12<=$D21),1,0) -> 0 | M21: =IF(AND(M$12>=$C21,M$12<=$D21),1,0) -> 1 | ... BG21: =IF(AND(BG$12>=$C21,BG$12<=$D21),1,0) -> 0
A22: ULEB energy model and Zone Green filing | C22: 2 | D22: 4 | F22: =IF(AND(F$12>=$C22,F$12<=$D22),1,0) -> 0 | G22: =IF(AND(G$12>=$C22,G$12<=$D22),1,0) -> 0 | H22: =IF(AND(H$12>=$C22,H$12<=$D22),1,0) -> 0 | I22: =IF(AND(I$12>=$C22,I$12<=$D22),1,0) -> 0 | J22: =IF(AND(J$12>=$C22,J$12<=$D22),1,0) -> 0 | K22: =IF(AND(K$12>=$C22,K$12<=$D22),1,0) -> 0 | L22: =IF(AND(L$12>=$C22,L$12<=$D22),1,0) -> 0 | M22: =IF(AND(M$12>=$C22,M$12<=$D22),1,0) -> 0 | ... BG22: =IF(AND(BG$12>=$C22,BG$12<=$D22),1,0) -> 0
A23: Offering plan drafted and submitted to the AG | C23: 3 | D23: 6 | F23: =IF(AND(F$12>=$C23,F$12<=$D23),1,0) -> 0 | G23: =IF(AND(G$12>=$C23,G$12<=$D23),1,0) -> 0 | H23: =IF(AND(H$12>=$C23,H$12<=$D23),1,0) -> 0 | I23: =IF(AND(I$12>=$C23,I$12<=$D23),1,0) -> 0 | J23: =IF(AND(J$12>=$C23,J$12<=$D23),1,0) -> 0 | K23: =IF(AND(K$12>=$C23,K$12<=$D23),1,0) -> 0 | L23: =IF(AND(L$12>=$C23,L$12<=$D23),1,0) -> 0 | M23: =IF(AND(M$12>=$C23,M$12<=$D23),1,0) -> 0 | ... BG23: =IF(AND(BG$12>=$C23,BG$12<=$D23),1,0) -> 0
A24: Buildings Department approvals and permits | C24: 4 | D24: 6 | F24: =IF(AND(F$12>=$C24,F$12<=$D24),1,0) -> 0 | G24: =IF(AND(G$12>=$C24,G$12<=$D24),1,0) -> 0 | H24: =IF(AND(H$12>=$C24,H$12<=$D24),1,0) -> 0 | I24: =IF(AND(I$12>=$C24,I$12<=$D24),1,0) -> 0 | J24: =IF(AND(J$12>=$C24,J$12<=$D24),1,0) -> 0 | K24: =IF(AND(K$12>=$C24,K$12<=$D24),1,0) -> 0 | L24: =IF(AND(L$12>=$C24,L$12<=$D24),1,0) -> 0 | M24: =IF(AND(M$12>=$C24,M$12<=$D24),1,0) -> 0 | ... BG24: =IF(AND(BG$12>=$C24,BG$12<=$D24),1,0) -> 0
A25: GC bidding and buyout | C25: 4 | D25: 6 | F25: =IF(AND(F$12>=$C25,F$12<=$D25),1,0) -> 0 | G25: =IF(AND(G$12>=$C25,G$12<=$D25),1,0) -> 0 | H25: =IF(AND(H$12>=$C25,H$12<=$D25),1,0) -> 0 | I25: =IF(AND(I$12>=$C25,I$12<=$D25),1,0) -> 0 | J25: =IF(AND(J$12>=$C25,J$12<=$D25),1,0) -> 0 | K25: =IF(AND(K$12>=$C25,K$12<=$D25),1,0) -> 0 | L25: =IF(AND(L$12>=$C25,L$12<=$D25),1,0) -> 0 | M25: =IF(AND(M$12>=$C25,M$12<=$D25),1,0) -> 0 | ... BG25: =IF(AND(BG$12>=$C25,BG$12<=$D25),1,0) -> 0
A26: Construction loan closing | C26: 6 | D26: 6 | F26: =IF(AND(F$12>=$C26,F$12<=$D26),1,0) -> 0 | G26: =IF(AND(G$12>=$C26,G$12<=$D26),1,0) -> 0 | H26: =IF(AND(H$12>=$C26,H$12<=$D26),1,0) -> 0 | I26: =IF(AND(I$12>=$C26,I$12<=$D26),1,0) -> 0 | J26: =IF(AND(J$12>=$C26,J$12<=$D26),1,0) -> 0 | K26: =IF(AND(K$12>=$C26,K$12<=$D26),1,0) -> 0 | L26: =IF(AND(L$12>=$C26,L$12<=$D26),1,0) -> 0 | M26: =IF(AND(M$12>=$C26,M$12<=$D26),1,0) -> 0 | ... BG26: =IF(AND(BG$12>=$C26,BG$12<=$D26),1,0) -> 0
A28: CONSTRUCTION DRAWS | F28: Start and end are construction months (1 = first month of construction). Cells show $ thousands drawn that month.
A29: Substructure and shell
A30: Excavation and soil removal | B30: ='Hard Costs'!$G$62 -> 61200 | C30: 2 | D30: 4 | F30: =IF(AND(F$12-$B$7>=$C30,F$12-$B$7<=$D30),$B30/($D30-$C30+1),0) -> 0 | G30: =IF(AND(G$12-$B$7>=$C30,G$12-$B$7<=$D30),$B30/($D30-$C30+1),0) -> 0 | H30: =IF(AND(H$12-$B$7>=$C30,H$12-$B$7<=$D30),$B30/($D30-$C30+1),0) -> 0 | I30: =IF(AND(I$12-$B$7>=$C30,I$12-$B$7<=$D30),$B30/($D30-$C30+1),0) -> 0 | J30: =IF(AND(J$12-$B$7>=$C30,J$12-$B$7<=$D30),$B30/($D30-$C30+1),0) -> 0 | K30: =IF(AND(K$12-$B$7>=$C30,K$12-$B$7<=$D30),$B30/($D30-$C30+1),0) -> 0 | L30: =IF(AND(L$12-$B$7>=$C30,L$12-$B$7<=$D30),$B30/($D30-$C30+1),0) -> 0 | M30: =IF(AND(M$12-$B$7>=$C30,M$12-$B$7<=$D30),$B30/($D30-$C30+1),0) -> 0 | ... BG30: =IF(AND(BG$12-$B$7>=$C30,BG$12-$B$7<=$D30),$B30/($D30-$C30+1),0) -> 0
A31: Dewatering and support of excavation | B31: ='Hard Costs'!$G$63 -> 70000 | C31: 2 | D31: 4 | F31: =IF(AND(F$12-$B$7>=$C31,F$12-$B$7<=$D31),$B31/($D31-$C31+1),0) -> 0 | G31: =IF(AND(G$12-$B$7>=$C31,G$12-$B$7<=$D31),$B31/($D31-$C31+1),0) -> 0 | H31: =IF(AND(H$12-$B$7>=$C31,H$12-$B$7<=$D31),$B31/($D31-$C31+1),0) -> 0 | I31: =IF(AND(I$12-$B$7>=$C31,I$12-$B$7<=$D31),$B31/($D31-$C31+1),0) -> 0 | J31: =IF(AND(J$12-$B$7>=$C31,J$12-$B$7<=$D31),$B31/($D31-$C31+1),0) -> 0 | K31: =IF(AND(K$12-$B$7>=$C31,K$12-$B$7<=$D31),$B31/($D31-$C31+1),0) -> 0 | L31: =IF(AND(L$12-$B$7>=$C31,L$12-$B$7<=$D31),$B31/($D31-$C31+1),0) -> 0 | M31: =IF(AND(M$12-$B$7>=$C31,M$12-$B$7<=$D31),$B31/($D31-$C31+1),0) -> 0 | ... BG31: =IF(AND(BG$12-$B$7>=$C31,BG$12-$B$7<=$D31),$B31/($D31-$C31+1),0) -> 0
A32: Underpinning and shoring at shared lot lines | B32: ='Hard Costs'!$G$64 -> 234000 | C32: 2 | D32: 4 | F32: =IF(AND(F$12-$B$7>=$C32,F$12-$B$7<=$D32),$B32/($D32-$C32+1),0) -> 0 | G32: =IF(AND(G$12-$B$7>=$C32,G$12-$B$7<=$D32),$B32/($D32-$C32+1),0) -> 0 | H32: =IF(AND(H$12-$B$7>=$C32,H$12-$B$7<=$D32),$B32/($D32-$C32+1),0) -> 0 | I32: =IF(AND(I$12-$B$7>=$C32,I$12-$B$7<=$D32),$B32/($D32-$C32+1),0) -> 0 | J32: =IF(AND(J$12-$B$7>=$C32,J$12-$B$7<=$D32),$B32/($D32-$C32+1),0) -> 0 | K32: =IF(AND(K$12-$B$7>=$C32,K$12-$B$7<=$D32),$B32/($D32-$C32+1),0) -> 0 | L32: =IF(AND(L$12-$B$7>=$C32,L$12-$B$7<=$D32),$B32/($D32-$C32+1),0) -> 0 | M32: =IF(AND(M$12-$B$7>=$C32,M$12-$B$7<=$D32),$B32/($D32-$C32+1),0) -> 0 | ... BG32: =IF(AND(BG$12-$B$7>=$C32,BG$12-$B$7<=$D32),$B32/($D32-$C32+1),0) -> 0
A33: Footings and foundation walls | B33: ='Hard Costs'!$G$65 -> 101660 | C33: 4 | D33: 6 | F33: =IF(AND(F$12-$B$7>=$C33,F$12-$B$7<=$D33),$B33/($D33-$C33+1),0) -> 0 | G33: =IF(AND(G$12-$B$7>=$C33,G$12-$B$7<=$D33),$B33/($D33-$C33+1),0) -> 0 | H33: =IF(AND(H$12-$B$7>=$C33,H$12-$B$7<=$D33),$B33/($D33-$C33+1),0) -> 0 | I33: =IF(AND(I$12-$B$7>=$C33,I$12-$B$7<=$D33),$B33/($D33-$C33+1),0) -> 0 | J33: =IF(AND(J$12-$B$7>=$C33,J$12-$B$7<=$D33),$B33/($D33-$C33+1),0) -> 0 | K33: =IF(AND(K$12-$B$7>=$C33,K$12-$B$7<=$D33),$B33/($D33-$C33+1),0) -> 0 | L33: =IF(AND(L$12-$B$7>=$C33,L$12-$B$7<=$D33),$B33/($D33-$C33+1),0) -> 0 | M33: =IF(AND(M$12-$B$7>=$C33,M$12-$B$7<=$D33),$B33/($D33-$C33+1),0) -> 0 | ... BG33: =IF(AND(BG$12-$B$7>=$C33,BG$12-$B$7<=$D33),$B33/($D33-$C33+1),0) -> 0
A34: Cellar slab, waterproofing and vapour barrier | B34: ='Hard Costs'!$G$66 -> 55080 | C34: 5 | D34: 6 | F34: =IF(AND(F$12-$B$7>=$C34,F$12-$B$7<=$D34),$B34/($D34-$C34+1),0) -> 0 | G34: =IF(AND(G$12-$B$7>=$C34,G$12-$B$7<=$D34),$B34/($D34-$C34+1),0) -> 0 | H34: =IF(AND(H$12-$B$7>=$C34,H$12-$B$7<=$D34),$B34/($D34-$C34+1),0) -> 0 | I34: =IF(AND(I$12-$B$7>=$C34,I$12-$B$7<=$D34),$B34/($D34-$C34+1),0) -> 0 | J34: =IF(AND(J$12-$B$7>=$C34,J$12-$B$7<=$D34),$B34/($D34-$C34+1),0) -> 0 | K34: =IF(AND(K$12-$B$7>=$C34,K$12-$B$7<=$D34),$B34/($D34-$C34+1),0) -> 0 | L34: =IF(AND(L$12-$B$7>=$C34,L$12-$B$7<=$D34),$B34/($D34-$C34+1),0) -> 0 | M34: =IF(AND(M$12-$B$7>=$C34,M$12-$B$7<=$D34),$B34/($D34-$C34+1),0) -> 0 | ... BG34: =IF(AND(BG$12-$B$7>=$C34,BG$12-$B$7<=$D34),$B34/($D34-$C34+1),0) -> 0
A35: Demolition of the existing building | B35: ='Hard Costs'!$G$67 -> 0 | C35: 1 | D35: 2 | F35: =IF(AND(F$12-$B$7>=$C35,F$12-$B$7<=$D35),$B35/($D35-$C35+1),0) -> 0 | G35: =IF(AND(G$12-$B$7>=$C35,G$12-$B$7<=$D35),$B35/($D35-$C35+1),0) -> 0 | H35: =IF(AND(H$12-$B$7>=$C35,H$12-$B$7<=$D35),$B35/($D35-$C35+1),0) -> 0 | I35: =IF(AND(I$12-$B$7>=$C35,I$12-$B$7<=$D35),$B35/($D35-$C35+1),0) -> 0 | J35: =IF(AND(J$12-$B$7>=$C35,J$12-$B$7<=$D35),$B35/($D35-$C35+1),0) -> 0 | K35: =IF(AND(K$12-$B$7>=$C35,K$12-$B$7<=$D35),$B35/($D35-$C35+1),0) -> 0 | L35: =IF(AND(L$12-$B$7>=$C35,L$12-$B$7<=$D35),$B35/($D35-$C35+1),0) -> 0 | M35: =IF(AND(M$12-$B$7>=$C35,M$12-$B$7<=$D35),$B35/($D35-$C35+1),0) -> 0 | ... BG35: =IF(AND(BG$12-$B$7>=$C35,BG$12-$B$7<=$D35),$B35/($D35-$C35+1),0) -> 0
A36: Superstructure, ground to roof | B36: ='Hard Costs'!$G$68 -> 180829.65 | C36: 6 | D36: 11 | F36: =IF(AND(F$12-$B$7>=$C36,F$12-$B$7<=$D36),$B36/($D36-$C36+1),0) -> 0 | G36: =IF(AND(G$12-$B$7>=$C36,G$12-$B$7<=$D36),$B36/($D36-$C36+1),0) -> 0 | H36: =IF(AND(H$12-$B$7>=$C36,H$12-$B$7<=$D36),$B36/($D36-$C36+1),0) -> 0 | I36: =IF(AND(I$12-$B$7>=$C36,I$12-$B$7<=$D36),$B36/($D36-$C36+1),0) -> 0 | J36: =IF(AND(J$12-$B$7>=$C36,J$12-$B$7<=$D36),$B36/($D36-$C36+1),0) -> 0 | K36: =IF(AND(K$12-$B$7>=$C36,K$12-$B$7<=$D36),$B36/($D36-$C36+1),0) -> 0 | L36: =IF(AND(L$12-$B$7>=$C36,L$12-$B$7<=$D36),$B36/($D36-$C36+1),0) -> 0 | M36: =IF(AND(M$12-$B$7>=$C36,M$12-$B$7<=$D36),$B36/($D36-$C36+1),0) -> 0 | ... BG36: =IF(AND(BG$12-$B$7>=$C36,BG$12-$B$7<=$D36),$B36/($D36-$C36+1),0) -> 0
A37: Super Structure - Floor Slab | B37: ='Hard Costs'!$G$69 -> 435540 | C37: 6 | D37: 11 | F37: =IF(AND(F$12-$B$7>=$C37,F$12-$B$7<=$D37),$B37/($D37-$C37+1),0) -> 0 | G37: =IF(AND(G$12-$B$7>=$C37,G$12-$B$7<=$D37),$B37/($D37-$C37+1),0) -> 0 | H37: =IF(AND(H$12-$B$7>=$C37,H$12-$B$7<=$D37),$B37/($D37-$C37+1),0) -> 0 | I37: =IF(AND(I$12-$B$7>=$C37,I$12-$B$7<=$D37),$B37/($D37-$C37+1),0) -> 0 | J37: =IF(AND(J$12-$B$7>=$C37,J$12-$B$7<=$D37),$B37/($D37-$C37+1),0) -> 0 | K37: =IF(AND(K$12-$B$7>=$C37,K$12-$B$7<=$D37),$B37/($D37-$C37+1),0) -> 0 | L37: =IF(AND(L$12-$B$7>=$C37,L$12-$B$7<=$D37),$B37/($D37-$C37+1),0) -> 0 | M37: =IF(AND(M$12-$B$7>=$C37,M$12-$B$7<=$D37),$B37/($D37-$C37+1),0) -> 0 | ... BG37: =IF(AND(BG$12-$B$7>=$C37,BG$12-$B$7<=$D37),$B37/($D37-$C37+1),0) -> 0
A38: Rooftop MEP penthouse | B38: ='Hard Costs'!$G$70 -> 0 | C38: 11 | D38: 12 | F38: =IF(AND(F$12-$B$7>=$C38,F$12-$B$7<=$D38),$B38/($D38-$C38+1),0) -> 0 | G38: =IF(AND(G$12-$B$7>=$C38,G$12-$B$7<=$D38),$B38/($D38-$C38+1),0) -> 0 | H38: =IF(AND(H$12-$B$7>=$C38,H$12-$B$7<=$D38),$B38/($D38-$C38+1),0) -> 0 | I38: =IF(AND(I$12-$B$7>=$C38,I$12-$B$7<=$D38),$B38/($D38-$C38+1),0) -> 0 | J38: =IF(AND(J$12-$B$7>=$C38,J$12-$B$7<=$D38),$B38/($D38-$C38+1),0) -> 0 | K38: =IF(AND(K$12-$B$7>=$C38,K$12-$B$7<=$D38),$B38/($D38-$C38+1),0) -> 0 | L38: =IF(AND(L$12-$B$7>=$C38,L$12-$B$7<=$D38),$B38/($D38-$C38+1),0) -> 0 | M38: =IF(AND(M$12-$B$7>=$C38,M$12-$B$7<=$D38),$B38/($D38-$C38+1),0) -> 0 | ... BG38: =IF(AND(BG$12-$B$7>=$C38,BG$12-$B$7<=$D38),$B38/($D38-$C38+1),0) -> 0
A39: Envelope
A40: Windows: high-performance double-pane, street walls | B40: ='Hard Costs'!$G$73 -> 176000 | C40: 10 | D40: 15 | F40: =IF(AND(F$12-$B$7>=$C40,F$12-$B$7<=$D40),$B40/($D40-$C40+1),0) -> 0 | G40: =IF(AND(G$12-$B$7>=$C40,G$12-$B$7<=$D40),$B40/($D40-$C40+1),0) -> 0 | H40: =IF(AND(H$12-$B$7>=$C40,H$12-$B$7<=$D40),$B40/($D40-$C40+1),0) -> 0 | I40: =IF(AND(I$12-$B$7>=$C40,I$12-$B$7<=$D40),$B40/($D40-$C40+1),0) -> 0 | J40: =IF(AND(J$12-$B$7>=$C40,J$12-$B$7<=$D40),$B40/($D40-$C40+1),0) -> 0 | K40: =IF(AND(K$12-$B$7>=$C40,K$12-$B$7<=$D40),$B40/($D40-$C40+1),0) -> 0 | L40: =IF(AND(L$12-$B$7>=$C40,L$12-$B$7<=$D40),$B40/($D40-$C40+1),0) -> 0 | M40: =IF(AND(M$12-$B$7>=$C40,M$12-$B$7<=$D40),$B40/($D40-$C40+1),0) -> 0 | ... BG40: =IF(AND(BG$12-$B$7>=$C40,BG$12-$B$7<=$D40),$B40/($D40-$C40+1),0) -> 0
A41: Insulated opaque wall, street walls | B41: ='Hard Costs'!$G$74 -> 148500 | C41: 10 | D41: 15 | F41: =IF(AND(F$12-$B$7>=$C41,F$12-$B$7<=$D41),$B41/($D41-$C41+1),0) -> 0 | G41: =IF(AND(G$12-$B$7>=$C41,G$12-$B$7<=$D41),$B41/($D41-$C41+1),0) -> 0 | H41: =IF(AND(H$12-$B$7>=$C41,H$12-$B$7<=$D41),$B41/($D41-$C41+1),0) -> 0 | I41: =IF(AND(I$12-$B$7>=$C41,I$12-$B$7<=$D41),$B41/($D41-$C41+1),0) -> 0 | J41: =IF(AND(J$12-$B$7>=$C41,J$12-$B$7<=$D41),$B41/($D41-$C41+1),0) -> 0 | K41: =IF(AND(K$12-$B$7>=$C41,K$12-$B$7<=$D41),$B41/($D41-$C41+1),0) -> 0 | L41: =IF(AND(L$12-$B$7>=$C41,L$12-$B$7<=$D41),$B41/($D41-$C41+1),0) -> 0 | M41: =IF(AND(M$12-$B$7>=$C41,M$12-$B$7<=$D41),$B41/($D41-$C41+1),0) -> 0 | ... BG41: =IF(AND(BG$12-$B$7>=$C41,BG$12-$B$7<=$D41),$B41/($D41-$C41+1),0) -> 0
A42: Lot-line and party walls | B42: ='Hard Costs'!$G$75 -> 448140 | C42: 8 | D42: 13 | F42: =IF(AND(F$12-$B$7>=$C42,F$12-$B$7<=$D42),$B42/($D42-$C42+1),0) -> 0 | G42: =IF(AND(G$12-$B$7>=$C42,G$12-$B$7<=$D42),$B42/($D42-$C42+1),0) -> 0 | H42: =IF(AND(H$12-$B$7>=$C42,H$12-$B$7<=$D42),$B42/($D42-$C42+1),0) -> 0 | I42: =IF(AND(I$12-$B$7>=$C42,I$12-$B$7<=$D42),$B42/($D42-$C42+1),0) -> 0 | J42: =IF(AND(J$12-$B$7>=$C42,J$12-$B$7<=$D42),$B42/($D42-$C42+1),0) -> 0 | K42: =IF(AND(K$12-$B$7>=$C42,K$12-$B$7<=$D42),$B42/($D42-$C42+1),0) -> 0 | L42: =IF(AND(L$12-$B$7>=$C42,L$12-$B$7<=$D42),$B42/($D42-$C42+1),0) -> 0 | M42: =IF(AND(M$12-$B$7>=$C42,M$12-$B$7<=$D42),$B42/($D42-$C42+1),0) -> 0 | ... BG42: =IF(AND(BG$12-$B$7>=$C42,BG$12-$B$7<=$D42),$B42/($D42-$C42+1),0) -> 0
A43: Façade fins (none in this design) | B43: ='Hard Costs'!$G$76 -> 0 | C43: 14 | D43: 16 | F43: =IF(AND(F$12-$B$7>=$C43,F$12-$B$7<=$D43),$B43/($D43-$C43+1),0) -> 0 | G43: =IF(AND(G$12-$B$7>=$C43,G$12-$B$7<=$D43),$B43/($D43-$C43+1),0) -> 0 | H43: =IF(AND(H$12-$B$7>=$C43,H$12-$B$7<=$D43),$B43/($D43-$C43+1),0) -> 0 | I43: =IF(AND(I$12-$B$7>=$C43,I$12-$B$7<=$D43),$B43/($D43-$C43+1),0) -> 0 | J43: =IF(AND(J$12-$B$7>=$C43,J$12-$B$7<=$D43),$B43/($D43-$C43+1),0) -> 0 | K43: =IF(AND(K$12-$B$7>=$C43,K$12-$B$7<=$D43),$B43/($D43-$C43+1),0) -> 0 | L43: =IF(AND(L$12-$B$7>=$C43,L$12-$B$7<=$D43),$B43/($D43-$C43+1),0) -> 0 | M43: =IF(AND(M$12-$B$7>=$C43,M$12-$B$7<=$D43),$B43/($D43-$C43+1),0) -> 0 | ... BG43: =IF(AND(BG$12-$B$7>=$C43,BG$12-$B$7<=$D43),$B43/($D43-$C43+1),0) -> 0
A44: Roofing, waterproofing and flashing | B44: ='Hard Costs'!$G$77 -> 192014 | C44: 11 | D44: 13 | F44: =IF(AND(F$12-$B$7>=$C44,F$12-$B$7<=$D44),$B44/($D44-$C44+1),0) -> 0 | G44: =IF(AND(G$12-$B$7>=$C44,G$12-$B$7<=$D44),$B44/($D44-$C44+1),0) -> 0 | H44: =IF(AND(H$12-$B$7>=$C44,H$12-$B$7<=$D44),$B44/($D44-$C44+1),0) -> 0 | I44: =IF(AND(I$12-$B$7>=$C44,I$12-$B$7<=$D44),$B44/($D44-$C44+1),0) -> 0 | J44: =IF(AND(J$12-$B$7>=$C44,J$12-$B$7<=$D44),$B44/($D44-$C44+1),0) -> 0 | K44: =IF(AND(K$12-$B$7>=$C44,K$12-$B$7<=$D44),$B44/($D44-$C44+1),0) -> 0 | L44: =IF(AND(L$12-$B$7>=$C44,L$12-$B$7<=$D44),$B44/($D44-$C44+1),0) -> 0 | M44: =IF(AND(M$12-$B$7>=$C44,M$12-$B$7<=$D44),$B44/($D44-$C44+1),0) -> 0 | ... BG44: =IF(AND(BG$12-$B$7>=$C44,BG$12-$B$7<=$D44),$B44/($D44-$C44+1),0) -> 0
A45: Solar panels or green roof | B45: ='Hard Costs'!$G$78 -> 60000 | C45: 17 | D45: 19 | F45: =IF(AND(F$12-$B$7>=$C45,F$12-$B$7<=$D45),$B45/($D45-$C45+1),0) -> 0 | G45: =IF(AND(G$12-$B$7>=$C45,G$12-$B$7<=$D45),$B45/($D45-$C45+1),0) -> 0 | H45: =IF(AND(H$12-$B$7>=$C45,H$12-$B$7<=$D45),$B45/($D45-$C45+1),0) -> 0 | I45: =IF(AND(I$12-$B$7>=$C45,I$12-$B$7<=$D45),$B45/($D45-$C45+1),0) -> 0 | J45: =IF(AND(J$12-$B$7>=$C45,J$12-$B$7<=$D45),$B45/($D45-$C45+1),0) -> 0 | K45: =IF(AND(K$12-$B$7>=$C45,K$12-$B$7<=$D45),$B45/($D45-$C45+1),0) -> 0 | L45: =IF(AND(L$12-$B$7>=$C45,L$12-$B$7<=$D45),$B45/($D45-$C45+1),0) -> 0 | M45: =IF(AND(M$12-$B$7>=$C45,M$12-$B$7<=$D45),$B45/($D45-$C45+1),0) -> 0 | ... BG45: =IF(AND(BG$12-$B$7>=$C45,BG$12-$B$7<=$D45),$B45/($D45-$C45+1),0) -> 0
A46: Core and systems
A47: Elevator, one car | B47: ='Hard Costs'!$G$81 -> 495000 | C47: 12 | D47: 18 | F47: =IF(AND(F$12-$B$7>=$C47,F$12-$B$7<=$D47),$B47/($D47-$C47+1),0) -> 0 | G47: =IF(AND(G$12-$B$7>=$C47,G$12-$B$7<=$D47),$B47/($D47-$C47+1),0) -> 0 | H47: =IF(AND(H$12-$B$7>=$C47,H$12-$B$7<=$D47),$B47/($D47-$C47+1),0) -> 0 | I47: =IF(AND(I$12-$B$7>=$C47,I$12-$B$7<=$D47),$B47/($D47-$C47+1),0) -> 0 | J47: =IF(AND(J$12-$B$7>=$C47,J$12-$B$7<=$D47),$B47/($D47-$C47+1),0) -> 0 | K47: =IF(AND(K$12-$B$7>=$C47,K$12-$B$7<=$D47),$B47/($D47-$C47+1),0) -> 0 | L47: =IF(AND(L$12-$B$7>=$C47,L$12-$B$7<=$D47),$B47/($D47-$C47+1),0) -> 0 | M47: =IF(AND(M$12-$B$7>=$C47,M$12-$B$7<=$D47),$B47/($D47-$C47+1),0) -> 0 | ... BG47: =IF(AND(BG$12-$B$7>=$C47,BG$12-$B$7<=$D47),$B47/($D47-$C47+1),0) -> 0
A48: Scissor stair, flights, railings and risers | B48: ='Hard Costs'!$G$82 -> 198000 | C48: 7 | D48: 12 | F48: =IF(AND(F$12-$B$7>=$C48,F$12-$B$7<=$D48),$B48/($D48-$C48+1),0) -> 0 | G48: =IF(AND(G$12-$B$7>=$C48,G$12-$B$7<=$D48),$B48/($D48-$C48+1),0) -> 0 | H48: =IF(AND(H$12-$B$7>=$C48,H$12-$B$7<=$D48),$B48/($D48-$C48+1),0) -> 0 | I48: =IF(AND(I$12-$B$7>=$C48,I$12-$B$7<=$D48),$B48/($D48-$C48+1),0) -> 0 | J48: =IF(AND(J$12-$B$7>=$C48,J$12-$B$7<=$D48),$B48/($D48-$C48+1),0) -> 0 | K48: =IF(AND(K$12-$B$7>=$C48,K$12-$B$7<=$D48),$B48/($D48-$C48+1),0) -> 0 | L48: =IF(AND(L$12-$B$7>=$C48,L$12-$B$7<=$D48),$B48/($D48-$C48+1),0) -> 0 | M48: =IF(AND(M$12-$B$7>=$C48,M$12-$B$7<=$D48),$B48/($D48-$C48+1),0) -> 0 | ... BG48: =IF(AND(BG$12-$B$7>=$C48,BG$12-$B$7<=$D48),$B48/($D48-$C48+1),0) -> 0
A49: MEP, residential: plumbing, electrical and distribution | B49: ='Hard Costs'!$G$83 -> 270000 | C49: 9 | D49: 16 | F49: =IF(AND(F$12-$B$7>=$C49,F$12-$B$7<=$D49),$B49/($D49-$C49+1),0) -> 0 | G49: =IF(AND(G$12-$B$7>=$C49,G$12-$B$7<=$D49),$B49/($D49-$C49+1),0) -> 0 | H49: =IF(AND(H$12-$B$7>=$C49,H$12-$B$7<=$D49),$B49/($D49-$C49+1),0) -> 0 | I49: =IF(AND(I$12-$B$7>=$C49,I$12-$B$7<=$D49),$B49/($D49-$C49+1),0) -> 0 | J49: =IF(AND(J$12-$B$7>=$C49,J$12-$B$7<=$D49),$B49/($D49-$C49+1),0) -> 0 | K49: =IF(AND(K$12-$B$7>=$C49,K$12-$B$7<=$D49),$B49/($D49-$C49+1),0) -> 0 | L49: =IF(AND(L$12-$B$7>=$C49,L$12-$B$7<=$D49),$B49/($D49-$C49+1),0) -> 0 | M49: =IF(AND(M$12-$B$7>=$C49,M$12-$B$7<=$D49),$B49/($D49-$C49+1),0) -> 0 | ... BG49: =IF(AND(BG$12-$B$7>=$C49,BG$12-$B$7<=$D49),$B49/($D49-$C49+1),0) -> 0
A50: Heat pumps: heating and cooling | B50: ='Hard Costs'!$G$84 -> 162000 | C50: 13 | D50: 17 | F50: =IF(AND(F$12-$B$7>=$C50,F$12-$B$7<=$D50),$B50/($D50-$C50+1),0) -> 0 | G50: =IF(AND(G$12-$B$7>=$C50,G$12-$B$7<=$D50),$B50/($D50-$C50+1),0) -> 0 | H50: =IF(AND(H$12-$B$7>=$C50,H$12-$B$7<=$D50),$B50/($D50-$C50+1),0) -> 0 | I50: =IF(AND(I$12-$B$7>=$C50,I$12-$B$7<=$D50),$B50/($D50-$C50+1),0) -> 0 | J50: =IF(AND(J$12-$B$7>=$C50,J$12-$B$7<=$D50),$B50/($D50-$C50+1),0) -> 0 | K50: =IF(AND(K$12-$B$7>=$C50,K$12-$B$7<=$D50),$B50/($D50-$C50+1),0) -> 0 | L50: =IF(AND(L$12-$B$7>=$C50,L$12-$B$7<=$D50),$B50/($D50-$C50+1),0) -> 0 | M50: =IF(AND(M$12-$B$7>=$C50,M$12-$B$7<=$D50),$B50/($D50-$C50+1),0) -> 0 | ... BG50: =IF(AND(BG$12-$B$7>=$C50,BG$12-$B$7<=$D50),$B50/($D50-$C50+1),0) -> 0
A51: ERVs: energy recovery ventilation | B51: ='Hard Costs'!$G$85 -> 54000 | C51: 13 | D51: 17 | F51: =IF(AND(F$12-$B$7>=$C51,F$12-$B$7<=$D51),$B51/($D51-$C51+1),0) -> 0 | G51: =IF(AND(G$12-$B$7>=$C51,G$12-$B$7<=$D51),$B51/($D51-$C51+1),0) -> 0 | H51: =IF(AND(H$12-$B$7>=$C51,H$12-$B$7<=$D51),$B51/($D51-$C51+1),0) -> 0 | I51: =IF(AND(I$12-$B$7>=$C51,I$12-$B$7<=$D51),$B51/($D51-$C51+1),0) -> 0 | J51: =IF(AND(J$12-$B$7>=$C51,J$12-$B$7<=$D51),$B51/($D51-$C51+1),0) -> 0 | K51: =IF(AND(K$12-$B$7>=$C51,K$12-$B$7<=$D51),$B51/($D51-$C51+1),0) -> 0 | L51: =IF(AND(L$12-$B$7>=$C51,L$12-$B$7<=$D51),$B51/($D51-$C51+1),0) -> 0 | M51: =IF(AND(M$12-$B$7>=$C51,M$12-$B$7<=$D51),$B51/($D51-$C51+1),0) -> 0 | ... BG51: =IF(AND(BG$12-$B$7>=$C51,BG$12-$B$7<=$D51),$B51/($D51-$C51+1),0) -> 0
A52: Heat-pump water heaters | B52: ='Hard Costs'!$G$86 -> 36000 | C52: 14 | D52: 16 | F52: =IF(AND(F$12-$B$7>=$C52,F$12-$B$7<=$D52),$B52/($D52-$C52+1),0) -> 0 | G52: =IF(AND(G$12-$B$7>=$C52,G$12-$B$7<=$D52),$B52/($D52-$C52+1),0) -> 0 | H52: =IF(AND(H$12-$B$7>=$C52,H$12-$B$7<=$D52),$B52/($D52-$C52+1),0) -> 0 | I52: =IF(AND(I$12-$B$7>=$C52,I$12-$B$7<=$D52),$B52/($D52-$C52+1),0) -> 0 | J52: =IF(AND(J$12-$B$7>=$C52,J$12-$B$7<=$D52),$B52/($D52-$C52+1),0) -> 0 | K52: =IF(AND(K$12-$B$7>=$C52,K$12-$B$7<=$D52),$B52/($D52-$C52+1),0) -> 0 | L52: =IF(AND(L$12-$B$7>=$C52,L$12-$B$7<=$D52),$B52/($D52-$C52+1),0) -> 0 | M52: =IF(AND(M$12-$B$7>=$C52,M$12-$B$7<=$D52),$B52/($D52-$C52+1),0) -> 0 | ... BG52: =IF(AND(BG$12-$B$7>=$C52,BG$12-$B$7<=$D52),$B52/($D52-$C52+1),0) -> 0
A53: Electric service upgrade (Con Ed), all-electric building | B53: ='Hard Costs'!$G$87 -> 75000 | C53: 15 | D53: 17 | F53: =IF(AND(F$12-$B$7>=$C53,F$12-$B$7<=$D53),$B53/($D53-$C53+1),0) -> 0 | G53: =IF(AND(G$12-$B$7>=$C53,G$12-$B$7<=$D53),$B53/($D53-$C53+1),0) -> 0 | H53: =IF(AND(H$12-$B$7>=$C53,H$12-$B$7<=$D53),$B53/($D53-$C53+1),0) -> 0 | I53: =IF(AND(I$12-$B$7>=$C53,I$12-$B$7<=$D53),$B53/($D53-$C53+1),0) -> 0 | J53: =IF(AND(J$12-$B$7>=$C53,J$12-$B$7<=$D53),$B53/($D53-$C53+1),0) -> 0 | K53: =IF(AND(K$12-$B$7>=$C53,K$12-$B$7<=$D53),$B53/($D53-$C53+1),0) -> 0 | L53: =IF(AND(L$12-$B$7>=$C53,L$12-$B$7<=$D53),$B53/($D53-$C53+1),0) -> 0 | M53: =IF(AND(M$12-$B$7>=$C53,M$12-$B$7<=$D53),$B53/($D53-$C53+1),0) -> 0 | ... BG53: =IF(AND(BG$12-$B$7>=$C53,BG$12-$B$7<=$D53),$B53/($D53-$C53+1),0) -> 0
A54: MEP, commercial core and shell (1st and 2nd floors) | B54: ='Hard Costs'!$G$88 -> 121324 | C54: 12 | D54: 16 | F54: =IF(AND(F$12-$B$7>=$C54,F$12-$B$7<=$D54),$B54/($D54-$C54+1),0) -> 0 | G54: =IF(AND(G$12-$B$7>=$C54,G$12-$B$7<=$D54),$B54/($D54-$C54+1),0) -> 0 | H54: =IF(AND(H$12-$B$7>=$C54,H$12-$B$7<=$D54),$B54/($D54-$C54+1),0) -> 0 | I54: =IF(AND(I$12-$B$7>=$C54,I$12-$B$7<=$D54),$B54/($D54-$C54+1),0) -> 0 | J54: =IF(AND(J$12-$B$7>=$C54,J$12-$B$7<=$D54),$B54/($D54-$C54+1),0) -> 0 | K54: =IF(AND(K$12-$B$7>=$C54,K$12-$B$7<=$D54),$B54/($D54-$C54+1),0) -> 0 | L54: =IF(AND(L$12-$B$7>=$C54,L$12-$B$7<=$D54),$B54/($D54-$C54+1),0) -> 0 | M54: =IF(AND(M$12-$B$7>=$C54,M$12-$B$7<=$D54),$B54/($D54-$C54+1),0) -> 0 | ... BG54: =IF(AND(BG$12-$B$7>=$C54,BG$12-$B$7<=$D54),$B54/($D54-$C54+1),0) -> 0
A55: Sprinkler, standpipe and fire alarm | B55: ='Hard Costs'!$G$89 -> 246092 | C55: 9 | D55: 15 | F55: =IF(AND(F$12-$B$7>=$C55,F$12-$B$7<=$D55),$B55/($D55-$C55+1),0) -> 0 | G55: =IF(AND(G$12-$B$7>=$C55,G$12-$B$7<=$D55),$B55/($D55-$C55+1),0) -> 0 | H55: =IF(AND(H$12-$B$7>=$C55,H$12-$B$7<=$D55),$B55/($D55-$C55+1),0) -> 0 | I55: =IF(AND(I$12-$B$7>=$C55,I$12-$B$7<=$D55),$B55/($D55-$C55+1),0) -> 0 | J55: =IF(AND(J$12-$B$7>=$C55,J$12-$B$7<=$D55),$B55/($D55-$C55+1),0) -> 0 | K55: =IF(AND(K$12-$B$7>=$C55,K$12-$B$7<=$D55),$B55/($D55-$C55+1),0) -> 0 | L55: =IF(AND(L$12-$B$7>=$C55,L$12-$B$7<=$D55),$B55/($D55-$C55+1),0) -> 0 | M55: =IF(AND(M$12-$B$7>=$C55,M$12-$B$7<=$D55),$B55/($D55-$C55+1),0) -> 0 | ... BG55: =IF(AND(BG$12-$B$7>=$C55,BG$12-$B$7<=$D55),$B55/($D55-$C55+1),0) -> 0
A56: Fit-out
A57: Unit walls: demising, corridor and core (fire-rated) | B57: ='Hard Costs'!$G$92 -> 57750 | C57: 12 | D57: 15 | F57: =IF(AND(F$12-$B$7>=$C57,F$12-$B$7<=$D57),$B57/($D57-$C57+1),0) -> 0 | G57: =IF(AND(G$12-$B$7>=$C57,G$12-$B$7<=$D57),$B57/($D57-$C57+1),0) -> 0 | H57: =IF(AND(H$12-$B$7>=$C57,H$12-$B$7<=$D57),$B57/($D57-$C57+1),0) -> 0 | I57: =IF(AND(I$12-$B$7>=$C57,I$12-$B$7<=$D57),$B57/($D57-$C57+1),0) -> 0 | J57: =IF(AND(J$12-$B$7>=$C57,J$12-$B$7<=$D57),$B57/($D57-$C57+1),0) -> 0 | K57: =IF(AND(K$12-$B$7>=$C57,K$12-$B$7<=$D57),$B57/($D57-$C57+1),0) -> 0 | L57: =IF(AND(L$12-$B$7>=$C57,L$12-$B$7<=$D57),$B57/($D57-$C57+1),0) -> 0 | M57: =IF(AND(M$12-$B$7>=$C57,M$12-$B$7<=$D57),$B57/($D57-$C57+1),0) -> 0 | ... BG57: =IF(AND(BG$12-$B$7>=$C57,BG$12-$B$7<=$D57),$B57/($D57-$C57+1),0) -> 0
A58: Partitions inside units | B58: ='Hard Costs'!$G$93 -> 54450 | C58: 13 | D58: 16 | F58: =IF(AND(F$12-$B$7>=$C58,F$12-$B$7<=$D58),$B58/($D58-$C58+1),0) -> 0 | G58: =IF(AND(G$12-$B$7>=$C58,G$12-$B$7<=$D58),$B58/($D58-$C58+1),0) -> 0 | H58: =IF(AND(H$12-$B$7>=$C58,H$12-$B$7<=$D58),$B58/($D58-$C58+1),0) -> 0 | I58: =IF(AND(I$12-$B$7>=$C58,I$12-$B$7<=$D58),$B58/($D58-$C58+1),0) -> 0 | J58: =IF(AND(J$12-$B$7>=$C58,J$12-$B$7<=$D58),$B58/($D58-$C58+1),0) -> 0 | K58: =IF(AND(K$12-$B$7>=$C58,K$12-$B$7<=$D58),$B58/($D58-$C58+1),0) -> 0 | L58: =IF(AND(L$12-$B$7>=$C58,L$12-$B$7<=$D58),$B58/($D58-$C58+1),0) -> 0 | M58: =IF(AND(M$12-$B$7>=$C58,M$12-$B$7<=$D58),$B58/($D58-$C58+1),0) -> 0 | ... BG58: =IF(AND(BG$12-$B$7>=$C58,BG$12-$B$7<=$D58),$B58/($D58-$C58+1),0) -> 0
A59: Unit entry doors (fire-rated) | B59: ='Hard Costs'!$G$94 -> 22500 | C59: 16 | D59: 17 | F59: =IF(AND(F$12-$B$7>=$C59,F$12-$B$7<=$D59),$B59/($D59-$C59+1),0) -> 0 | G59: =IF(AND(G$12-$B$7>=$C59,G$12-$B$7<=$D59),$B59/($D59-$C59+1),0) -> 0 | H59: =IF(AND(H$12-$B$7>=$C59,H$12-$B$7<=$D59),$B59/($D59-$C59+1),0) -> 0 | I59: =IF(AND(I$12-$B$7>=$C59,I$12-$B$7<=$D59),$B59/($D59-$C59+1),0) -> 0 | J59: =IF(AND(J$12-$B$7>=$C59,J$12-$B$7<=$D59),$B59/($D59-$C59+1),0) -> 0 | K59: =IF(AND(K$12-$B$7>=$C59,K$12-$B$7<=$D59),$B59/($D59-$C59+1),0) -> 0 | L59: =IF(AND(L$12-$B$7>=$C59,L$12-$B$7<=$D59),$B59/($D59-$C59+1),0) -> 0 | M59: =IF(AND(M$12-$B$7>=$C59,M$12-$B$7<=$D59),$B59/($D59-$C59+1),0) -> 0 | ... BG59: =IF(AND(BG$12-$B$7>=$C59,BG$12-$B$7<=$D59),$B59/($D59-$C59+1),0) -> 0
A60: Interior doors | B60: ='Hard Costs'!$G$95 -> 56400 | C60: 16 | D60: 18 | F60: =IF(AND(F$12-$B$7>=$C60,F$12-$B$7<=$D60),$B60/($D60-$C60+1),0) -> 0 | G60: =IF(AND(G$12-$B$7>=$C60,G$12-$B$7<=$D60),$B60/($D60-$C60+1),0) -> 0 | H60: =IF(AND(H$12-$B$7>=$C60,H$12-$B$7<=$D60),$B60/($D60-$C60+1),0) -> 0 | I60: =IF(AND(I$12-$B$7>=$C60,I$12-$B$7<=$D60),$B60/($D60-$C60+1),0) -> 0 | J60: =IF(AND(J$12-$B$7>=$C60,J$12-$B$7<=$D60),$B60/($D60-$C60+1),0) -> 0 | K60: =IF(AND(K$12-$B$7>=$C60,K$12-$B$7<=$D60),$B60/($D60-$C60+1),0) -> 0 | L60: =IF(AND(L$12-$B$7>=$C60,L$12-$B$7<=$D60),$B60/($D60-$C60+1),0) -> 0 | M60: =IF(AND(M$12-$B$7>=$C60,M$12-$B$7<=$D60),$B60/($D60-$C60+1),0) -> 0 | ... BG60: =IF(AND(BG$12-$B$7>=$C60,BG$12-$B$7<=$D60),$B60/($D60-$C60+1),0) -> 0
A61: Flooring | B61: ='Hard Costs'!$G$96 -> 68790 | C61: 17 | D61: 19 | F61: =IF(AND(F$12-$B$7>=$C61,F$12-$B$7<=$D61),$B61/($D61-$C61+1),0) -> 0 | G61: =IF(AND(G$12-$B$7>=$C61,G$12-$B$7<=$D61),$B61/($D61-$C61+1),0) -> 0 | H61: =IF(AND(H$12-$B$7>=$C61,H$12-$B$7<=$D61),$B61/($D61-$C61+1),0) -> 0 | I61: =IF(AND(I$12-$B$7>=$C61,I$12-$B$7<=$D61),$B61/($D61-$C61+1),0) -> 0 | J61: =IF(AND(J$12-$B$7>=$C61,J$12-$B$7<=$D61),$B61/($D61-$C61+1),0) -> 0 | K61: =IF(AND(K$12-$B$7>=$C61,K$12-$B$7<=$D61),$B61/($D61-$C61+1),0) -> 0 | L61: =IF(AND(L$12-$B$7>=$C61,L$12-$B$7<=$D61),$B61/($D61-$C61+1),0) -> 0 | M61: =IF(AND(M$12-$B$7>=$C61,M$12-$B$7<=$D61),$B61/($D61-$C61+1),0) -> 0 | ... BG61: =IF(AND(BG$12-$B$7>=$C61,BG$12-$B$7<=$D61),$B61/($D61-$C61+1),0) -> 0
A62: Paint | B62: ='Hard Costs'!$G$97 -> 90000 | C62: 18 | D62: 19 | F62: =IF(AND(F$12-$B$7>=$C62,F$12-$B$7<=$D62),$B62/($D62-$C62+1),0) -> 0 | G62: =IF(AND(G$12-$B$7>=$C62,G$12-$B$7<=$D62),$B62/($D62-$C62+1),0) -> 0 | H62: =IF(AND(H$12-$B$7>=$C62,H$12-$B$7<=$D62),$B62/($D62-$C62+1),0) -> 0 | I62: =IF(AND(I$12-$B$7>=$C62,I$12-$B$7<=$D62),$B62/($D62-$C62+1),0) -> 0 | J62: =IF(AND(J$12-$B$7>=$C62,J$12-$B$7<=$D62),$B62/($D62-$C62+1),0) -> 0 | K62: =IF(AND(K$12-$B$7>=$C62,K$12-$B$7<=$D62),$B62/($D62-$C62+1),0) -> 0 | L62: =IF(AND(L$12-$B$7>=$C62,L$12-$B$7<=$D62),$B62/($D62-$C62+1),0) -> 0 | M62: =IF(AND(M$12-$B$7>=$C62,M$12-$B$7<=$D62),$B62/($D62-$C62+1),0) -> 0 | ... BG62: =IF(AND(BG$12-$B$7>=$C62,BG$12-$B$7<=$D62),$B62/($D62-$C62+1),0) -> 0
A63: Unit interiors: trim, closets, hardware and ceilings | B63: ='Hard Costs'!$G$98 -> 206370 | C63: 17 | D63: 19 | F63: =IF(AND(F$12-$B$7>=$C63,F$12-$B$7<=$D63),$B63/($D63-$C63+1),0) -> 0 | G63: =IF(AND(G$12-$B$7>=$C63,G$12-$B$7<=$D63),$B63/($D63-$C63+1),0) -> 0 | H63: =IF(AND(H$12-$B$7>=$C63,H$12-$B$7<=$D63),$B63/($D63-$C63+1),0) -> 0 | I63: =IF(AND(I$12-$B$7>=$C63,I$12-$B$7<=$D63),$B63/($D63-$C63+1),0) -> 0 | J63: =IF(AND(J$12-$B$7>=$C63,J$12-$B$7<=$D63),$B63/($D63-$C63+1),0) -> 0 | K63: =IF(AND(K$12-$B$7>=$C63,K$12-$B$7<=$D63),$B63/($D63-$C63+1),0) -> 0 | L63: =IF(AND(L$12-$B$7>=$C63,L$12-$B$7<=$D63),$B63/($D63-$C63+1),0) -> 0 | M63: =IF(AND(M$12-$B$7>=$C63,M$12-$B$7<=$D63),$B63/($D63-$C63+1),0) -> 0 | ... BG63: =IF(AND(BG$12-$B$7>=$C63,BG$12-$B$7<=$D63),$B63/($D63-$C63+1),0) -> 0
A64: Kitchen cabinets | B64: ='Hard Costs'!$G$99 -> 162000 | C64: 16 | D64: 19 | F64: =IF(AND(F$12-$B$7>=$C64,F$12-$B$7<=$D64),$B64/($D64-$C64+1),0) -> 0 | G64: =IF(AND(G$12-$B$7>=$C64,G$12-$B$7<=$D64),$B64/($D64-$C64+1),0) -> 0 | H64: =IF(AND(H$12-$B$7>=$C64,H$12-$B$7<=$D64),$B64/($D64-$C64+1),0) -> 0 | I64: =IF(AND(I$12-$B$7>=$C64,I$12-$B$7<=$D64),$B64/($D64-$C64+1),0) -> 0 | J64: =IF(AND(J$12-$B$7>=$C64,J$12-$B$7<=$D64),$B64/($D64-$C64+1),0) -> 0 | K64: =IF(AND(K$12-$B$7>=$C64,K$12-$B$7<=$D64),$B64/($D64-$C64+1),0) -> 0 | L64: =IF(AND(L$12-$B$7>=$C64,L$12-$B$7<=$D64),$B64/($D64-$C64+1),0) -> 0 | M64: =IF(AND(M$12-$B$7>=$C64,M$12-$B$7<=$D64),$B64/($D64-$C64+1),0) -> 0 | ... BG64: =IF(AND(BG$12-$B$7>=$C64,BG$12-$B$7<=$D64),$B64/($D64-$C64+1),0) -> 0
A65: Kitchen appliances (induction) | B65: ='Hard Costs'!$G$100 -> 108000 | C65: 18 | D65: 20 | F65: =IF(AND(F$12-$B$7>=$C65,F$12-$B$7<=$D65),$B65/($D65-$C65+1),0) -> 0 | G65: =IF(AND(G$12-$B$7>=$C65,G$12-$B$7<=$D65),$B65/($D65-$C65+1),0) -> 0 | H65: =IF(AND(H$12-$B$7>=$C65,H$12-$B$7<=$D65),$B65/($D65-$C65+1),0) -> 0 | I65: =IF(AND(I$12-$B$7>=$C65,I$12-$B$7<=$D65),$B65/($D65-$C65+1),0) -> 0 | J65: =IF(AND(J$12-$B$7>=$C65,J$12-$B$7<=$D65),$B65/($D65-$C65+1),0) -> 0 | K65: =IF(AND(K$12-$B$7>=$C65,K$12-$B$7<=$D65),$B65/($D65-$C65+1),0) -> 0 | L65: =IF(AND(L$12-$B$7>=$C65,L$12-$B$7<=$D65),$B65/($D65-$C65+1),0) -> 0 | M65: =IF(AND(M$12-$B$7>=$C65,M$12-$B$7<=$D65),$B65/($D65-$C65+1),0) -> 0 | ... BG65: =IF(AND(BG$12-$B$7>=$C65,BG$12-$B$7<=$D65),$B65/($D65-$C65+1),0) -> 0
A66: Bathrooms | B66: ='Hard Costs'!$G$101 -> 168000 | C66: 15 | D66: 18 | F66: =IF(AND(F$12-$B$7>=$C66,F$12-$B$7<=$D66),$B66/($D66-$C66+1),0) -> 0 | G66: =IF(AND(G$12-$B$7>=$C66,G$12-$B$7<=$D66),$B66/($D66-$C66+1),0) -> 0 | H66: =IF(AND(H$12-$B$7>=$C66,H$12-$B$7<=$D66),$B66/($D66-$C66+1),0) -> 0 | I66: =IF(AND(I$12-$B$7>=$C66,I$12-$B$7<=$D66),$B66/($D66-$C66+1),0) -> 0 | J66: =IF(AND(J$12-$B$7>=$C66,J$12-$B$7<=$D66),$B66/($D66-$C66+1),0) -> 0 | K66: =IF(AND(K$12-$B$7>=$C66,K$12-$B$7<=$D66),$B66/($D66-$C66+1),0) -> 0 | L66: =IF(AND(L$12-$B$7>=$C66,L$12-$B$7<=$D66),$B66/($D66-$C66+1),0) -> 0 | M66: =IF(AND(M$12-$B$7>=$C66,M$12-$B$7<=$D66),$B66/($D66-$C66+1),0) -> 0 | ... BG66: =IF(AND(BG$12-$B$7>=$C66,BG$12-$B$7<=$D66),$B66/($D66-$C66+1),0) -> 0
A67: Private bulkhead and roof skylight | B67: ='Hard Costs'!$G$102 -> 85000 | C67: 14 | D67: 17 | F67: =IF(AND(F$12-$B$7>=$C67,F$12-$B$7<=$D67),$B67/($D67-$C67+1),0) -> 0 | G67: =IF(AND(G$12-$B$7>=$C67,G$12-$B$7<=$D67),$B67/($D67-$C67+1),0) -> 0 | H67: =IF(AND(H$12-$B$7>=$C67,H$12-$B$7<=$D67),$B67/($D67-$C67+1),0) -> 0 | I67: =IF(AND(I$12-$B$7>=$C67,I$12-$B$7<=$D67),$B67/($D67-$C67+1),0) -> 0 | J67: =IF(AND(J$12-$B$7>=$C67,J$12-$B$7<=$D67),$B67/($D67-$C67+1),0) -> 0 | K67: =IF(AND(K$12-$B$7>=$C67,K$12-$B$7<=$D67),$B67/($D67-$C67+1),0) -> 0 | L67: =IF(AND(L$12-$B$7>=$C67,L$12-$B$7<=$D67),$B67/($D67-$C67+1),0) -> 0 | M67: =IF(AND(M$12-$B$7>=$C67,M$12-$B$7<=$D67),$B67/($D67-$C67+1),0) -> 0 | ... BG67: =IF(AND(BG$12-$B$7>=$C67,BG$12-$B$7<=$D67),$B67/($D67-$C67+1),0) -> 0
A68: Cellar commercial and community facility fit-out | B68: ='Hard Costs'!$G$103 -> 111420 | C68: 17 | D68: 20 | F68: =IF(AND(F$12-$B$7>=$C68,F$12-$B$7<=$D68),$B68/($D68-$C68+1),0) -> 0 | G68: =IF(AND(G$12-$B$7>=$C68,G$12-$B$7<=$D68),$B68/($D68-$C68+1),0) -> 0 | H68: =IF(AND(H$12-$B$7>=$C68,H$12-$B$7<=$D68),$B68/($D68-$C68+1),0) -> 0 | I68: =IF(AND(I$12-$B$7>=$C68,I$12-$B$7<=$D68),$B68/($D68-$C68+1),0) -> 0 | J68: =IF(AND(J$12-$B$7>=$C68,J$12-$B$7<=$D68),$B68/($D68-$C68+1),0) -> 0 | K68: =IF(AND(K$12-$B$7>=$C68,K$12-$B$7<=$D68),$B68/($D68-$C68+1),0) -> 0 | L68: =IF(AND(L$12-$B$7>=$C68,L$12-$B$7<=$D68),$B68/($D68-$C68+1),0) -> 0 | M68: =IF(AND(M$12-$B$7>=$C68,M$12-$B$7<=$D68),$B68/($D68-$C68+1),0) -> 0 | ... BG68: =IF(AND(BG$12-$B$7>=$C68,BG$12-$B$7<=$D68),$B68/($D68-$C68+1),0) -> 0
A69: Cellar commercial: second exit and code upgrades | B69: ='Hard Costs'!$G$104 -> 40000 | C69: 17 | D69: 20 | F69: =IF(AND(F$12-$B$7>=$C69,F$12-$B$7<=$D69),$B69/($D69-$C69+1),0) -> 0 | G69: =IF(AND(G$12-$B$7>=$C69,G$12-$B$7<=$D69),$B69/($D69-$C69+1),0) -> 0 | H69: =IF(AND(H$12-$B$7>=$C69,H$12-$B$7<=$D69),$B69/($D69-$C69+1),0) -> 0 | I69: =IF(AND(I$12-$B$7>=$C69,I$12-$B$7<=$D69),$B69/($D69-$C69+1),0) -> 0 | J69: =IF(AND(J$12-$B$7>=$C69,J$12-$B$7<=$D69),$B69/($D69-$C69+1),0) -> 0 | K69: =IF(AND(K$12-$B$7>=$C69,K$12-$B$7<=$D69),$B69/($D69-$C69+1),0) -> 0 | L69: =IF(AND(L$12-$B$7>=$C69,L$12-$B$7<=$D69),$B69/($D69-$C69+1),0) -> 0 | M69: =IF(AND(M$12-$B$7>=$C69,M$12-$B$7<=$D69),$B69/($D69-$C69+1),0) -> 0 | ... BG69: =IF(AND(BG$12-$B$7>=$C69,BG$12-$B$7<=$D69),$B69/($D69-$C69+1),0) -> 0
A70: Corridors, lobby and core finishes | B70: ='Hard Costs'!$G$105 -> 242675 | C70: 17 | D70: 19 | F70: =IF(AND(F$12-$B$7>=$C70,F$12-$B$7<=$D70),$B70/($D70-$C70+1),0) -> 0 | G70: =IF(AND(G$12-$B$7>=$C70,G$12-$B$7<=$D70),$B70/($D70-$C70+1),0) -> 0 | H70: =IF(AND(H$12-$B$7>=$C70,H$12-$B$7<=$D70),$B70/($D70-$C70+1),0) -> 0 | I70: =IF(AND(I$12-$B$7>=$C70,I$12-$B$7<=$D70),$B70/($D70-$C70+1),0) -> 0 | J70: =IF(AND(J$12-$B$7>=$C70,J$12-$B$7<=$D70),$B70/($D70-$C70+1),0) -> 0 | K70: =IF(AND(K$12-$B$7>=$C70,K$12-$B$7<=$D70),$B70/($D70-$C70+1),0) -> 0 | L70: =IF(AND(L$12-$B$7>=$C70,L$12-$B$7<=$D70),$B70/($D70-$C70+1),0) -> 0 | M70: =IF(AND(M$12-$B$7>=$C70,M$12-$B$7<=$D70),$B70/($D70-$C70+1),0) -> 0 | ... BG70: =IF(AND(BG$12-$B$7>=$C70,BG$12-$B$7<=$D70),$B70/($D70-$C70+1),0) -> 0
A71: Terraces, balconies and roof deck | B71: ='Hard Costs'!$G$106 -> 405975 | C71: 16 | D71: 19 | F71: =IF(AND(F$12-$B$7>=$C71,F$12-$B$7<=$D71),$B71/($D71-$C71+1),0) -> 0 | G71: =IF(AND(G$12-$B$7>=$C71,G$12-$B$7<=$D71),$B71/($D71-$C71+1),0) -> 0 | H71: =IF(AND(H$12-$B$7>=$C71,H$12-$B$7<=$D71),$B71/($D71-$C71+1),0) -> 0 | I71: =IF(AND(I$12-$B$7>=$C71,I$12-$B$7<=$D71),$B71/($D71-$C71+1),0) -> 0 | J71: =IF(AND(J$12-$B$7>=$C71,J$12-$B$7<=$D71),$B71/($D71-$C71+1),0) -> 0 | K71: =IF(AND(K$12-$B$7>=$C71,K$12-$B$7<=$D71),$B71/($D71-$C71+1),0) -> 0 | L71: =IF(AND(L$12-$B$7>=$C71,L$12-$B$7<=$D71),$B71/($D71-$C71+1),0) -> 0 | M71: =IF(AND(M$12-$B$7>=$C71,M$12-$B$7<=$D71),$B71/($D71-$C71+1),0) -> 0 | ... BG71: =IF(AND(BG$12-$B$7>=$C71,BG$12-$B$7<=$D71),$B71/($D71-$C71+1),0) -> 0
A72: Site and general
A73: Sidewalk, vault, utilities and site work | B73: ='Hard Costs'!$G$109 -> 21250 | C73: 18 | D73: 20 | F73: =IF(AND(F$12-$B$7>=$C73,F$12-$B$7<=$D73),$B73/($D73-$C73+1),0) -> 0 | G73: =IF(AND(G$12-$B$7>=$C73,G$12-$B$7<=$D73),$B73/($D73-$C73+1),0) -> 0 | H73: =IF(AND(H$12-$B$7>=$C73,H$12-$B$7<=$D73),$B73/($D73-$C73+1),0) -> 0 | I73: =IF(AND(I$12-$B$7>=$C73,I$12-$B$7<=$D73),$B73/($D73-$C73+1),0) -> 0 | J73: =IF(AND(J$12-$B$7>=$C73,J$12-$B$7<=$D73),$B73/($D73-$C73+1),0) -> 0 | K73: =IF(AND(K$12-$B$7>=$C73,K$12-$B$7<=$D73),$B73/($D73-$C73+1),0) -> 0 | L73: =IF(AND(L$12-$B$7>=$C73,L$12-$B$7<=$D73),$B73/($D73-$C73+1),0) -> 0 | M73: =IF(AND(M$12-$B$7>=$C73,M$12-$B$7<=$D73),$B73/($D73-$C73+1),0) -> 0 | ... BG73: =IF(AND(BG$12-$B$7>=$C73,BG$12-$B$7<=$D73),$B73/($D73-$C73+1),0) -> 0
A74: Environmental remediation allowance | B74: ='Hard Costs'!$G$110 -> 0 | C74: 1 | D74: 3 | F74: =IF(AND(F$12-$B$7>=$C74,F$12-$B$7<=$D74),$B74/($D74-$C74+1),0) -> 0 | G74: =IF(AND(G$12-$B$7>=$C74,G$12-$B$7<=$D74),$B74/($D74-$C74+1),0) -> 0 | H74: =IF(AND(H$12-$B$7>=$C74,H$12-$B$7<=$D74),$B74/($D74-$C74+1),0) -> 0 | I74: =IF(AND(I$12-$B$7>=$C74,I$12-$B$7<=$D74),$B74/($D74-$C74+1),0) -> 0 | J74: =IF(AND(J$12-$B$7>=$C74,J$12-$B$7<=$D74),$B74/($D74-$C74+1),0) -> 0 | K74: =IF(AND(K$12-$B$7>=$C74,K$12-$B$7<=$D74),$B74/($D74-$C74+1),0) -> 0 | L74: =IF(AND(L$12-$B$7>=$C74,L$12-$B$7<=$D74),$B74/($D74-$C74+1),0) -> 0 | M74: =IF(AND(M$12-$B$7>=$C74,M$12-$B$7<=$D74),$B74/($D74-$C74+1),0) -> 0 | ... BG74: =IF(AND(BG$12-$B$7>=$C74,BG$12-$B$7<=$D74),$B74/($D74-$C74+1),0) -> 0
A75: General conditions
A76: General conditions and GC fee | B76: ='Hard Costs'!$G$115 -> 572095.96 | C76: 1 | D76: =$B$8 -> 20 | F76: =IF(AND(F$12-$B$7>=$C76,F$12-$B$7<=$D76),$B76/($D76-$C76+1),0) -> 0 | G76: =IF(AND(G$12-$B$7>=$C76,G$12-$B$7<=$D76),$B76/($D76-$C76+1),0) -> 0 | H76: =IF(AND(H$12-$B$7>=$C76,H$12-$B$7<=$D76),$B76/($D76-$C76+1),0) -> 0 | I76: =IF(AND(I$12-$B$7>=$C76,I$12-$B$7<=$D76),$B76/($D76-$C76+1),0) -> 0 | J76: =IF(AND(J$12-$B$7>=$C76,J$12-$B$7<=$D76),$B76/($D76-$C76+1),0) -> 0 | K76: =IF(AND(K$12-$B$7>=$C76,K$12-$B$7<=$D76),$B76/($D76-$C76+1),0) -> 0 | L76: =IF(AND(L$12-$B$7>=$C76,L$12-$B$7<=$D76),$B76/($D76-$C76+1),0) -> 0 | M76: =IF(AND(M$12-$B$7>=$C76,M$12-$B$7<=$D76),$B76/($D76-$C76+1),0) -> 0 | ... BG76: =IF(AND(BG$12-$B$7>=$C76,BG$12-$B$7<=$D76),$B76/($D76-$C76+1),0) -> 0
A77: Trades plus general conditions | B77: =SUM(B29:B76) -> 6293055.6 | F77: =SUM(F29:F76) -> 0 | G77: =SUM(G29:G76) -> 0 | H77: =SUM(H29:H76) -> 0 | I77: =SUM(I29:I76) -> 0 | J77: =SUM(J29:J76) -> 0 | K77: =SUM(K29:K76) -> 0 | L77: =SUM(L29:L76) -> 0 | M77: =SUM(M29:M76) -> 0 | ... BG77: =SUM(BG29:BG76) -> 0
A78: Owner-budget adjustment, ULEB detailing and contingency, pro rata | B78: ='Hard Costs'!$G$121-B77 -> 240044.39 | F78: =$B$78*F77/$B$77 -> 0 | G78: =$B$78*G77/$B$77 -> 0 | H78: =$B$78*H77/$B$77 -> 0 | I78: =$B$78*I77/$B$77 -> 0 | J78: =$B$78*J77/$B$77 -> 0 | K78: =$B$78*K77/$B$77 -> 0 | L78: =$B$78*L77/$B$77 -> 0 | M78: =$B$78*M77/$B$77 -> 0 | ... BG78: =$B$78*BG77/$B$77 -> 0
A79: MONTHLY CONSTRUCTION DRAW | B79: =B77+B78 -> 6533100 | F79: =F77+F78 -> 0 | G79: =G77+G78 -> 0 | H79: =H77+H78 -> 0 | I79: =I77+I78 -> 0 | J79: =J77+J78 -> 0 | K79: =K77+K78 -> 0 | L79: =L77+L78 -> 0 | M79: =M77+M78 -> 0 | ... BG79: =BG77+BG78 -> 0
A80: Cash drawn to date | F80: =SUM($F$79:F79) -> 0 | G80: =SUM($F$79:G79) -> 0 | H80: =SUM($F$79:H79) -> 0 | I80: =SUM($F$79:I79) -> 0 | J80: =SUM($F$79:J79) -> 0 | K80: =SUM($F$79:K79) -> 0 | L80: =SUM($F$79:L79) -> 0 | M80: =SUM($F$79:M79) -> 0 | ... BG80: =SUM($F$79:BG79) -> 6533100
A81: Percent per month | F81: =IF(F79=0,"",F79/$B$79) | G81: =IF(G79=0,"",G79/$B$79) | H81: =IF(H79=0,"",H79/$B$79) | I81: =IF(I79=0,"",I79/$B$79) | J81: =IF(J79=0,"",J79/$B$79) | K81: =IF(K79=0,"",K79/$B$79) | L81: =IF(L79=0,"",L79/$B$79) | M81: =IF(M79=0,"",M79/$B$79) | ... BG81: =IF(BG79=0,"",BG79/$B$79)
A82: Percent complete to date | F82: =IF(F12<=$B$7,"",F80/$B$79) | G82: =IF(G12<=$B$7,"",G80/$B$79) | H82: =IF(H12<=$B$7,"",H80/$B$79) | I82: =IF(I12<=$B$7,"",I80/$B$79) | J82: =IF(J12<=$B$7,"",J80/$B$79) | K82: =IF(K12<=$B$7,"",K80/$B$79) | L82: =IF(L12<=$B$7,"",L80/$B$79) | M82: =IF(M12<=$B$7,"",M80/$B$79) | ... BG82: =IF(BG12<=$B$7,"",BG80/$B$79) -> 1
A83: Check: total draws less the Hard Costs total (should be 0) | B83: =SUM(F79:BG79)-'Hard Costs'!$G$121 -> 0
A85: SALES AND MILESTONES | F85: X marks a milestone. Unit closings come from the closing month of each unit on the Rev & Unit-by-Unit sheet.
A86: Presales of the standard units | C86: =$B$10 -> 12 | D86: =$B$7+$B$8 -> 26 | F86: =IF(AND(F$12>=$C86,F$12<=$D86),1,0) -> 0 | G86: =IF(AND(G$12>=$C86,G$12<=$D86),1,0) -> 0 | H86: =IF(AND(H$12>=$C86,H$12<=$D86),1,0) -> 0 | I86: =IF(AND(I$12>=$C86,I$12<=$D86),1,0) -> 0 | J86: =IF(AND(J$12>=$C86,J$12<=$D86),1,0) -> 0 | K86: =IF(AND(K$12>=$C86,K$12<=$D86),1,0) -> 0 | L86: =IF(AND(L$12>=$C86,L$12<=$D86),1,0) -> 0 | M86: =IF(AND(M$12>=$C86,M$12<=$D86),1,0) -> 0 | ... BG86: =IF(AND(BG$12>=$C86,BG$12<=$D86),1,0) -> 0
A87: Finish and stage the penthouse | C87: =$B$7+$B$8+1 -> 27 | D87: =$B$7+$B$8+2 -> 28 | F87: =IF(AND(F$12>=$C87,F$12<=$D87),1,0) -> 0 | G87: =IF(AND(G$12>=$C87,G$12<=$D87),1,0) -> 0 | H87: =IF(AND(H$12>=$C87,H$12<=$D87),1,0) -> 0 | I87: =IF(AND(I$12>=$C87,I$12<=$D87),1,0) -> 0 | J87: =IF(AND(J$12>=$C87,J$12<=$D87),1,0) -> 0 | K87: =IF(AND(K$12>=$C87,K$12<=$D87),1,0) -> 0 | L87: =IF(AND(L$12>=$C87,L$12<=$D87),1,0) -> 0 | M87: =IF(AND(M$12>=$C87,M$12<=$D87),1,0) -> 0 | ... BG87: =IF(AND(BG$12>=$C87,BG$12<=$D87),1,0) -> 0
A88: Land closing | C88: =0 -> 0 | F88: =IF(F$12=$C88,"X","") | G88: =IF(G$12=$C88,"X","") | H88: =IF(H$12=$C88,"X","") | I88: =IF(I$12=$C88,"X","") | J88: =IF(J$12=$C88,"X","") | K88: =IF(K$12=$C88,"X","") | L88: =IF(L$12=$C88,"X","") -> X | M88: =IF(M$12=$C88,"X","") | ... BG88: =IF(BG$12=$C88,"X","")
A89: Construction loan closes and construction starts | C89: =$B$7+1 -> 7 | F89: =IF(F$12=$C89,"X","") | G89: =IF(G$12=$C89,"X","") | H89: =IF(H$12=$C89,"X","") | I89: =IF(I$12=$C89,"X","") | J89: =IF(J$12=$C89,"X","") | K89: =IF(K$12=$C89,"X","") | L89: =IF(L$12=$C89,"X","") | M89: =IF(M$12=$C89,"X","") | ... BG89: =IF(BG$12=$C89,"X","")
A90: Offering plan accepted; presales launch | C90: =$B$10 -> 12 | F90: =IF(F$12=$C90,"X","") | G90: =IF(G$12=$C90,"X","") | H90: =IF(H$12=$C90,"X","") | I90: =IF(I$12=$C90,"X","") | J90: =IF(J$12=$C90,"X","") | K90: =IF(K$12=$C90,"X","") | L90: =IF(L$12=$C90,"X","") | M90: =IF(M$12=$C90,"X","") | ... BG90: =IF(BG$12=$C90,"X","")
A91: TCO: temporary certificate of occupancy | C91: =$B$7+$B$8 -> 26 | F91: =IF(F$12=$C91,"X","") | G91: =IF(G$12=$C91,"X","") | H91: =IF(H$12=$C91,"X","") | I91: =IF(I$12=$C91,"X","") | J91: =IF(J$12=$C91,"X","") | K91: =IF(K$12=$C91,"X","") | L91: =IF(L$12=$C91,"X","") | M91: =IF(M$12=$C91,"X","") | ... BG91: =IF(BG$12=$C91,"X","")
A92: Retail condo sale closes | C92: =$B$7+$B$8+Finance!$B$9 -> 27 | F92: =IF(F$12=$C92,"X","") | G92: =IF(G$12=$C92,"X","") | H92: =IF(H$12=$C92,"X","") | I92: =IF(I$12=$C92,"X","") | J92: =IF(J$12=$C92,"X","") | K92: =IF(K$12=$C92,"X","") | L92: =IF(L$12=$C92,"X","") | M92: =IF(M$12=$C92,"X","") | ... BG92: =IF(BG$12=$C92,"X","")
A93: Last unit closes; project complete | C93: =$B$7+$B$8+$B$9 -> 32 | F93: =IF(F$12=$C93,"X","") | G93: =IF(G$12=$C93,"X","") | H93: =IF(H$12=$C93,"X","") | I93: =IF(I$12=$C93,"X","") | J93: =IF(J$12=$C93,"X","") | K93: =IF(K$12=$C93,"X","") | L93: =IF(L$12=$C93,"X","") | M93: =IF(M$12=$C93,"X","") | ... BG93: =IF(BG$12=$C93,"X","")
A94: Unit closings (number of units) | F94: =IF(SUMPRODUCT(--('Rev & Unit-by-Unit'!$O$18:$O$26+$B$7+$B$8=F$12))=0,"",SUMPRODUCT(--('Rev & Unit-by-Unit'!$O$18:$O$26+$B$7+$B$8=F$12))) | G94: =IF(SUMPRODUCT(--('Rev & Unit-by-Unit'!$O$18:$O$26+$B$7+$B$8=G$12))=0,"",SUMPRODUCT(--('Rev & Unit-by-Unit'!$O$18:$O$26+$B$7+$B$8=G$12))) | H94: =IF(SUMPRODUCT(--('Rev & Unit-by-Unit'!$O$18:$O$26+$B$7+$B$8=H$12))=0,"",SUMPRODUCT(--('Rev & Unit-by-Unit'!$O$18:$O$26+$B$7+$B$8=H$12))) | I94: =IF(SUMPRODUCT(--('Rev & Unit-by-Unit'!$O$18:$O$26+$B$7+$B$8=I$12))=0,"",SUMPRODUCT(--('Rev & Unit-by-Unit'!$O$18:$O$26+$B$7+$B$8=I$12))) | J94: =IF(SUMPRODUCT(--('Rev & Unit-by-Unit'!$O$18:$O$26+$B$7+$B$8=J$12))=0,"",SUMPRODUCT(--('Rev & Unit-by-Unit'!$O$18:$O$26+$B$7+$B$8=J$12))) | K94: =IF(SUMPRODUCT(--('Rev & Unit-by-Unit'!$O$18:$O$26+$B$7+$B$8=K$12))=0,"",SUMPRODUCT(--('Rev & Unit-by-Unit'!$O$18:$O$26+$B$7+$B$8=K$12))) | L94: =IF(SUMPRODUCT(--('Rev & Unit-by-Unit'!$O$18:$O$26+$B$7+$B$8=L$12))=0,"",SUMPRODUCT(--('Rev & Unit-by-Unit'!$O$18:$O$26+$B$7+$B$8=L$12))) | M94: =IF(SUMPRODUCT(--('Rev & Unit-by-Unit'!$O$18:$O$26+$B$7+$B$8=M$12))=0,"",SUMPRODUCT(--('Rev & Unit-by-Unit'!$O$18:$O$26+$B$7+$B$8=M$12))) | ... BG94: =IF(SUMPRODUCT(--('Rev & Unit-by-Unit'!$O$18:$O$26+$B$7+$B$8=BG$12))=0,"",SUMPRODUCT(--('Rev & Unit-by-Unit'!$O$18:$O$26+$B$7+$B$8=BG$12)))
A96: Check: every unit closes within the sell-out period | B96: =IF('Rev & Unit-by-Unit'!$O$27<=$B$9,"OK","A unit closes after the sell-out period: extend it on Finance") -> OK

Sheet Hard Costs
A1: 246 South 2nd Street · Hard Cost Budget · Base
A2: 246 South 2nd Street on its own 3,100 sf lot in R6 with a commercial overlay: 8 stories at 85 ft (13'-11" ground floor, 11 ft 2nd floor, 10 ft above), plus a cellar and a private roof. 9 condos (8 market-rate and one affordable homeownership unit), 6,879 sellable sf; commercial on the 1st and 2nd floors (4,333 sf sellable) plus 1,857 sf in the cellar; Zone Green (ULEB) 5% exclusion; no air rights or certificates; all-electric.
A3: Blue cells are inputs. Black cells are formulas. Use the + / - buttons at the left edge to collapse the input blocks. Rates carry over from the 725 Grand budget as planning placeholders, not bids. Areas and lengths are measured from the 246 South 2nd Street floor area model (claude.ai artifact), October 18 2026.
A5: KEY AREAS
B6: Gross floor area above grade | C6: =$C$15 -> 14518 | D6: gsf | J6: Seven enclosed floors from the floor area model (see the formula row below).
B7: Cellar | C7: 3060 | D7: sf | J7: Full lot footprint (25 x 120 ft with the 30 ft wide rear 20 ft), less the lot-line offsets.
B8: Cellar depth | C8: 12 | D8: ft | J8: Cellar floor-to-floor, from the model. Used for the excavation volume.
B9: Commercial at grade (1st floor), sellable | C9: 1717 | D9: sf | J9: Model: sellable commercial on the 1st floor (2,344 gross less the lobby, core, corridor and 450 sf parking/loading).
B10: Net sellable residential | C10: =D34 -> 6879 | D10: sf | J10: Total of the unit mix below (offering-plan sf from the model).
B11: Common areas and core | C11: 2855 | D11: sf | J11: Gross above grade less residential and commercial sellable, less 450 sf parking: lobby, corridors, core, light-well walls and mechanical.
B12: Condo units | C12: =C34 -> 9 | D12: units | J12: Total of the unit mix below.
B13: Outer perimeter, all floors above grade | C13: 1810 | D13: Lf | J13: Model: 1st 239, 2nd 299, 4th-6th 230 each, 7th 212, 8th 171 Lf, plus about 40 Lf of light-well walls on floors 4-8.
B14: Rated walls around units | C14: 330 | D14: Lf | J14: Estimate: about 75 Lf of corridor and demising wall on each of floors 4-7, 30 Lf on the full-floor penthouse (8).
B15: Gross floor area above grade (formula) | C15: 14518 | D15: gsf | J15: Model: 1st 2,344 + 2nd 3,060 + 4th 2,035 + 5th 2,023 + 6th 2,020 + 7th 1,728 + 8th 1,308. The 3rd floor has no enclosed gross area in the model (2,467 sf common terrace and an amenity room).
B16: Street, rear and light-well wall area | C16: 5500 | D16: sf | J16: Street wall about 2,100 sf (to the 65 ft base plus the setback walls), rear walls about 1,900 sf, light-well walls about 1,500 sf.
B17: Cellar commercial and community facility area | C17: 1857 | D17: sf | J17: Model: 1,556 sf commercial plus 301 sf community facility in the cellar, sold with the commercial condo. Not zoning floor area.
B18: Stories above grade | C18: 8 | D18: floors | J18: Ground + 7, counting the 3rd-floor terrace level. Private roof above, no elevator stop there.
B19: Dormers | C19: 78 | D19: sf | J19: Model: one 7th-floor dormer in the street setback, 12'-4" x 6'-4" (ZR 23-413).
B20: Glazing share of street-facing wall | C20: 0.4 | D20: % | J20: A modest glass ratio is the cheapest way to meet the ULEB energy target that Zone Green needs.
B21: Hard-cost sensitivity adjustment | C21: 0 | D21: % | J21: Normally 0%. Scales the hard cost up or down, for testing (the OM sensitivity table uses it). Applies to the owner budget too.
B22: Commercial, 2nd floor, sellable | C22: 2616 | D22: sf | J22: Model: the full 2nd floor (3,060 gross less the 444 sf rear terrace).
B23: Owner's hard-cost budget | C23: 450 | D23: $ / gsf | J23: Owner, Oct 2026: $450 per gross sf, all in (trades, general conditions, fee and contingency).
B24: Area the owner's $ / gsf applies to | C24: =$C$6 -> 14518 | D24: gsf | J24: Gross above grade, the same basis as the 725 Grand $ / gsf measure. Owner to confirm: to include the 3,060 sf cellar, change this to =$C$6+$C$7 (+$1.38M).
B25: Use the owner's budget (1) or the line items (0) | C25: 1 | J25: 1: total hard cost = owner's budget; the line items stay as the detail and the gap goes on the adjustment line. 0: line items only.
A27: UNIT MIX
B28: Unit type | C28: Units | D28: Net sf per unit | E28: Partitions per unit (Lf) | F28: Interior doors per unit | G28: Baths per unit | J28: Notes
B29: Affordable 1-bedroom, floor 4 (4F), for sale | C29: 1 | D29: 858 | E29: 50 | F29: 5 | G29: 1 | J29: Affordable homeownership unit. Street side.
B30: 1-bedroom, rear, floors 4-7 (4R, 5R, 6R, 7R) | C30: 4 | D30: 718.75 | E30: 50 | F30: 5 | G30: 1 | J30: Model: 714, 719, 719 and 723 sf; each with a rear balcony.
B31: 2-bedroom, street, floors 5-6 (5F, 6F) | C31: 2 | D31: 858 | E31: 70 | F31: 6 | G31: 2 | J31: Two baths.
B32: Studio with street terrace, floor 7 (7F) | C32: 1 | D32: 567 | E32: 25 | F32: 3 | G32: 1 | J32: 292 sf private terrace on the 15 ft setback.
B33: Full-floor penthouse, floor 8, 2 bedrooms + private roof | C33: 1 | D33: 863 | E33: 80 | F33: 7 | G33: 2 | J33: Setback terrace and balcony (431 sf) plus a 1,505 sf private roof by a private stair.
B34: Total | C34: =SUM(C29:C33) -> 9 | D34: =SUMPRODUCT($C$29:$C$33,D29:D33) -> 6879 | E34: =SUMPRODUCT($C$29:$C$33,E29:E33) -> 495 | F34: =SUMPRODUCT($C$29:$C$33,F29:F33) -> 47 | G34: =SUMPRODUCT($C$29:$C$33,G29:G33) -> 12 | H34: 0 | J34: Units, total sellable sf, partition Lf, interior doors and baths. No duplex or mezzanine units.
A36: ZONING FLOOR AREA CHECK
B37: Lot area, 246 South 2nd Street | C37: 3100 | D37: sf | J37: 25 x 120 ft; the rear 20 ft is 30 ft wide. From the model.
B38: Total floor area ratio (R6 with qualifying affordable housing) | C38: 4.8 | D38: FAR | J38: Model zoning input. Counsel to confirm.
B39: Maximum zoning floor area, all uses | C39: =C37*C38 -> 14880 | D39: sf
B40: Market-rate residential floor area ratio | C40: 2.2 | D40: FAR | J40: Model zoning input.
B41: Market-rate residential allowed | C41: =C37*C40 -> 6820 | D41: sf
B42: Zone Green (ULEB) exclusion, taken off residential | C42: 627 | D42: sf | J42: Model: 5% of the 12,538 sf zoning floor area above grade. Needs an ultra low energy (Passive House level) building; without it the 5% is lost.
B43: Counted: market-rate residential, after the exclusion | C43: 6819 | D43: sf | J43: Model, floors 4-8 plus the core on the 1st floor.
B44: Counted: affordable residential (unit 4F) | C44: 858 | D44: sf | J44: Model. The affordable allowance input in the model is 700 sf, so its residential cap reads 157 sf over; confirm the affordable floor area rule.
B45: Counted: commercial, 1st and 2nd floors | C45: 4234 | D45: sf | J45: Model: 1st floor 1,174 + 2nd floor 3,060.
B46: Commercial allowed (2.0 FAR) | C46: =C37*2 -> 6200 | D46: sf
B47: Floor area counted for zoning, this design | C47: =C43+C44+C45 -> 11911 | D47: sf | J47: Matches the model total, 11,911 sf.
B48: Room left under the total | C48: =C39-C47 -> 2969 | D48: sf | J48: Unused floor area: about 2,969 sf, limited by the residential caps, height and the rear yard.
B49: Check: total floor area | C49: =IF(C48>=0,"PASS","OVER THE LIMIT") -> PASS
B50: Check: market-rate residential | C50: =IF(C43<=C41+0.5,"PASS","OVER THE LIMIT") -> PASS | J50: Counted is after the Zone Green exclusion.
B51: Check: commercial | C51: =IF(C45<=C46,"PASS","OVER THE LIMIT") -> PASS
B52: Building height | C52: 84.92 | D52: ft | J52: Model: cellar excluded; 13'-11" + 11 ft + six 10 ft floors = 84'-11".
B53: Height limit | C53: 85 | D53: ft | J53: R6 qualifying affordable housing, narrow street (ZR 23-432, 23-433); 65 ft base, 15 ft setback. Counsel to confirm.
B54: Check: height | C54: =IF(C52<=C53,"PASS","TOO TALL") -> PASS
A61: Group | B61: Line item | C61: Quantity | D61: Unit | E61: Rate | F61: Rate basis | G61: Total ($) | H61: $ / gsf | I61: % of hard | J61: Notes
A62: Substructure and shell | B62: Excavation and soil removal | C62: =$C$7*$C$8/27 -> 1360 | D62: cy | E62: 45 | F62: $ / cy | G62: =C62*E62 -> 61200 | H62: =G62/$C$6 -> 4.2154567 | I62: =G62/$G$121 -> 0.0093676815 | J62: Cellar area × depth ÷ 27.
A63: Substructure and shell | B63: Dewatering and support of excavation | C63: 1 | D63: allowance | E63: 70000 | F63: lump sum | G63: =C63*E63 -> 70000 | H63: =G63/$C$6 -> 4.8216008 | I63: =G63/$G$121 -> 0.010714668 | J63: Depends on the water table; confirm with the geotechnical report.
A64: Substructure and shell | B64: Underpinning and shoring at shared lot lines | C64: 195 | D64: Lf | E64: 1200 | F64: $ / Lf | G64: =C64*E64 -> 234000 | H64: =G64/$C$6 -> 16.117923 | I64: =G64/$G$121 -> 0.035817606 | J64: Survey: #242 (6-story) along the west lot line from 18.4 ft, #248 (1-story buildings) along the east lot line from 20 ft.
A65: Substructure and shell | B65: Footings and foundation walls | C65: 299 | D65: Lf | E65: 340 | F65: $ / Lf | G65: =C65*E65 -> 101660 | H65: =G65/$C$6 -> 7.0023419 | I65: =G65/$G$121 -> 0.01556076 | J65: Full cellar perimeter. Check with the structural engineer for an 8-story load.
A66: Substructure and shell | B66: Cellar slab, waterproofing and vapour barrier | C66: =$C$7 -> 3060 | D66: sf | E66: 18 | F66: $ / sf | G66: =C66*E66 -> 55080 | H66: =G66/$C$6 -> 3.793911 | I66: =G66/$G$121 -> 0.0084309133
A67: Substructure and shell | B67: Demolition of the existing building | C67: 0 | D67: sf | E67: 30 | F67: $ / sf | G67: =C67*E67 -> 0 | H67: =G67/$C$6 -> 0 | I67: =G67/$G$121 -> 0 | J67: None carried: confirm what stands on the lot today and add its area here at $30/sf.
A68: Substructure and shell | B68: Superstructure, ground to roof | C68: =$C$13*$C$52/(10*$C$18+5) -> 1808.2965 | D68: Lf of perimeter | E68: 100 | F68: $ / Lf | G68: =C68*E68 -> 180829.65 | H68: =G68/$C$6 -> 12.455548 | I68: =G68/$G$121 -> 0.027678996 | J68: Owner's $100/Lf on the summed outer perimeter, scaled by building height over a 10 ft-per-floor baseline.
A69: Substructure and shell | B69: Super Structure - Floor Slab | C69: =$C$6 -> 14518 | D69: sf | E69: 30 | F69: $ / sf | G69: =C69*E69 -> 435540 | H69: =G69/$C$6 -> 30 | I69: =G69/$G$121 -> 0.066666667 | J69: One structural slab per floor, on gross floor area above grade.
A70: Substructure and shell | B70: Rooftop MEP penthouse | C70: 0 | D70: gsf | E70: 70 | F70: $ / gsf | G70: =C70*E70 -> 0 | H70: =G70/$C$6 -> 0 | I70: =G70/$G$121 -> 0 | J70: None: mechanical in the cellar (343 sf) and in-unit closets; the roof is private outdoor space.
A71: Substructure and shell subtotal | G71: =SUM(G62:G70) -> 1138309.6 | H71: =G71/$C$6 -> 78.406781 | I71: =G71/$G$121 -> 0.17423729
A73: Envelope | B73: Windows: high-performance double-pane, street walls | C73: =$C$16*$C$20 -> 2200 | D73: sf of window | E73: 80 | F73: $ / sf | G73: =C73*E73 -> 176000 | H73: =G73/$C$6 -> 12.122882 | I73: =G73/$G$121 -> 0.026939738 | J73: Area = street wall × glazing share.
A74: Envelope | B74: Insulated opaque wall, street walls | C74: =$C$16*(1-$C$20) -> 3300 | D74: sf of wall | E74: 45 | F74: $ / sf | G74: =C74*E74 -> 148500 | H74: =G74/$C$6 -> 10.228682 | I74: =G74/$G$121 -> 0.022730404 | J74: Continuous exterior insulation and a sealed air barrier.
A75: Envelope | B75: Lot-line and party walls | C75: 10670 | D75: sf of wall | E75: 42 | F75: $ / sf | G75: =C75*E75 -> 448140 | H75: =G75/$C$6 -> 30.867888 | I75: =G75/$G$121 -> 0.068595307 | J75: Both side lot lines, floors 1-8 at their heights (11,670 sf), less the light well on the west lot line (about 1,000 sf).
A76: Envelope | B76: Façade fins (none in this design) | C76: 0 | D76: each | E76: 320 | F76: $ each | G76: =C76*E76 -> 0 | H76: =G76/$C$6 -> 0 | I76: =G76/$G$121 -> 0
A77: Envelope | B77: Roofing, waterproofing and flashing | C77: 5053 | D77: sf | E77: 38 | F77: $ / sf | G77: =C77*E77 -> 192014 | H77: =G77/$C$6 -> 13.225926 | I77: =G77/$G$121 -> 0.029390948 | J77: Main roof 1,505 + 3rd-floor common terrace 2,467 + 2nd-floor rear terrace 444 + 7th and 8th-floor terraces 637 sf.
A78: Envelope | B78: Solar panels or green roof | C78: 1 | D78: allowance | E78: 60000 | F78: lump sum | G78: =C78*E78 -> 60000 | H78: =G78/$C$6 -> 4.1328007 | I78: =G78/$G$121 -> 0.0091840015 | J78: NYC Local Laws 92 and 94 require solar or a green roof on new roofs.
A79: Envelope subtotal | G79: =SUM(G73:G78) -> 1024654 | H79: =G79/$C$6 -> 70.578179 | I79: =G79/$G$121 -> 0.1568404
A81: Core and systems | B81: Elevator, one car | C81: =$C$18+1 -> 9 | D81: stops | E81: 55000 | F81: $ / stop | G81: =C81*E81 -> 495000 | H81: =G81/$C$6 -> 34.095605 | I81: =G81/$G$121 -> 0.075768012 | J81: Cellar plus 8 floors; no stop at the private roof.
A82: Core and systems | B82: Scissor stair, flights, railings and risers | C82: =C81 -> 9 | D82: levels | E82: 22000 | F82: $ / level | G82: =C82*E82 -> 198000 | H82: =G82/$C$6 -> 13.638242 | I82: =G82/$G$121 -> 0.030307205 | J82: Same number of levels as elevator stops.
A83: Core and systems | B83: MEP, residential: plumbing, electrical and distribution | C83: =$C$12 -> 9 | D83: units | E83: 30000 | F83: $ / unit | G83: =C83*E83 -> 270000 | H83: =G83/$C$6 -> 18.597603 | I83: =G83/$G$121 -> 0.041328007 | J83: Owner's rate: $30,000 per unit, not including heating and cooling.
A84: Core and systems | B84: Heat pumps: heating and cooling | C84: =$C$12 -> 9 | D84: units | E84: 18000 | F84: $ / unit | G84: =C84*E84 -> 162000 | H84: =G84/$C$6 -> 11.158562 | I84: =G84/$G$121 -> 0.024796804 | J84: All-electric, no gas (NYC Local Law 154).
A85: Core and systems | B85: ERVs: energy recovery ventilation | C85: =$C$12 -> 9 | D85: units | E85: 6000 | F85: $ / unit | G85: =C85*E85 -> 54000 | H85: =G85/$C$6 -> 3.7195206 | I85: =G85/$G$121 -> 0.0082656013 | J85: Part of meeting the ULEB energy target.
A86: Core and systems | B86: Heat-pump water heaters | C86: =$C$12 -> 9 | D86: units | E86: 4000 | F86: $ / unit | G86: =C86*E86 -> 36000 | H86: =G86/$C$6 -> 2.4796804 | I86: =G86/$G$121 -> 0.0055104009
A87: Core and systems | B87: Electric service upgrade (Con Ed), all-electric building | C87: 1 | D87: allowance | E87: 75000 | F87: lump sum | G87: =C87*E87 -> 75000 | H87: =G87/$C$6 -> 5.1660008 | I87: =G87/$G$121 -> 0.011480002 | J87: Confirm with the MEP engineer for 9 units and the commercial floors.
A88: Core and systems | B88: MEP, commercial core and shell (1st and 2nd floors) | C88: =$C$9+$C$22 -> 4333 | D88: sf | E88: 28 | F88: $ / sf | G88: =C88*E88 -> 121324 | H88: =G88/$C$6 -> 8.3567985 | I88: =G88/$G$121 -> 0.018570663 | J88: Tenant fit-out not included.
A89: Core and systems | B89: Sprinkler, standpipe and fire alarm | C89: =$C$6+$C$7 -> 17578 | D89: gsf | E89: 14 | F89: $ / gsf | G89: =C89*E89 -> 246092 | H89: =G89/$C$6 -> 16.95082 | I89: =G89/$G$121 -> 0.037668488 | J89: Whole building including cellar.
A90: Core and systems subtotal | G90: =SUM(G81:G89) -> 1657416 | H90: =G90/$C$6 -> 114.16283 | I90: =G90/$G$121 -> 0.25369518
A92: Fit-out | B92: Unit walls: demising, corridor and core (fire-rated) | C92: =$C$14 -> 330 | D92: Lf | E92: 175 | F92: $ / Lf | G92: =C92*E92 -> 57750 | H92: =G92/$C$6 -> 3.9778206 | I92: =G92/$G$121 -> 0.0088396014 | J92: Rated metal stud and gypsum around every unit.
A93: Fit-out | B93: Partitions inside units | C93: =$E$34 -> 495 | D93: Lf | E93: 110 | F93: $ / Lf | G93: =C93*E93 -> 54450 | H93: =G93/$C$6 -> 3.7505166 | I93: =G93/$G$121 -> 0.0083344813 | J93: Unit mix × partitions per unit.
A94: Fit-out | B94: Unit entry doors (fire-rated) | C94: =$C$12 -> 9 | D94: doors | E94: 2500 | F94: $ each | G94: =C94*E94 -> 22500 | H94: =G94/$C$6 -> 1.5498002 | I94: =G94/$G$121 -> 0.0034440006
A95: Fit-out | B95: Interior doors | C95: =$F$34 -> 47 | D95: doors | E95: 1200 | F95: $ each | G95: =C95*E95 -> 56400 | H95: =G95/$C$6 -> 3.8848326 | I95: =G95/$G$121 -> 0.0086329614 | J95: Unit mix × doors per unit.
A96: Fit-out | B96: Flooring | C96: =$C$10 -> 6879 | D96: net sf | E96: 10 | F96: $ / sf | G96: =C96*E96 -> 68790 | H96: =G96/$C$6 -> 4.738256 | I96: =G96/$G$121 -> 0.010529458 | J96: Owner's rate.
A97: Fit-out | B97: Paint | C97: =$C$12 -> 9 | D97: units | E97: 10000 | F97: $ / unit | G97: =C97*E97 -> 90000 | H97: =G97/$C$6 -> 6.199201 | I97: =G97/$G$121 -> 0.013776002 | J97: Owner's rate.
A98: Fit-out | B98: Unit interiors: trim, closets, hardware and ceilings | C98: =$C$10 -> 6879 | D98: net sf | E98: 30 | F98: $ / sf | G98: =C98*E98 -> 206370 | H98: =G98/$C$6 -> 14.214768 | I98: =G98/$G$121 -> 0.031588373
A99: Fit-out | B99: Kitchen cabinets | C99: =$C$12 -> 9 | D99: kitchens | E99: 18000 | F99: $ each | G99: =C99*E99 -> 162000 | H99: =G99/$C$6 -> 11.158562 | I99: =G99/$G$121 -> 0.024796804 | J99: Owner, Oct 18 2026: cabinets and counters, split out of the old $30,000 kitchen line.
A100: Fit-out | B100: Kitchen appliances (induction) | C100: =$C$12 -> 9 | D100: kitchens | E100: 12000 | F100: $ each | G100: =C100*E100 -> 108000 | H100: =G100/$C$6 -> 7.4390412 | I100: =G100/$G$121 -> 0.016531203 | J100: Induction range, refrigerator, dishwasher, hood and microwave; all-electric.
A101: Fit-out | B101: Bathrooms | C101: =$G$34 -> 12 | D101: baths | E101: 14000 | F101: $ each | G101: =C101*E101 -> 168000 | H101: =G101/$C$6 -> 11.571842 | I101: =G101/$G$121 -> 0.025715204 | J101: From the unit mix; a powder room counts as half.
A102: Fit-out | B102: Private bulkhead and roof skylight | C102: 1 | D102: allowance | E102: 85000 | F102: lump sum | G102: =C102*E102 -> 85000 | H102: =G102/$C$6 -> 5.8548009 | I102: =G102/$G$121 -> 0.013010669 | J102: Private stair from the 8th-floor penthouse to its roof, with a hatch or bulkhead.
A103: Fit-out | B103: Cellar commercial and community facility fit-out | C103: =$C$17 -> 1857 | D103: sf | E103: 60 | F103: $ / sf | G103: =C103*E103 -> 111420 | H103: =G103/$C$6 -> 7.6746108 | I103: =G103/$G$121 -> 0.017054691 | J103: White-box finish for the below-grade space; tenants do their own fit-out.
A104: Fit-out | B104: Cellar commercial: second exit and code upgrades | C104: 1 | D104: allowance | E104: 40000 | F104: lump sum | G104: =C104*E104 -> 40000 | H104: =G104/$C$6 -> 2.7552004 | I104: =G104/$G$121 -> 0.0061226676 | J104: A second means of egress and separation to occupy the cellar.
A105: Fit-out | B105: Corridors, lobby and core finishes | C105: =$C$11 -> 2855 | D105: sf | E105: 85 | F105: $ / sf | G105: =C105*E105 -> 242675 | H105: =G105/$C$6 -> 16.715457 | I105: =G105/$G$121 -> 0.037145459
A106: Fit-out | B106: Terraces, balconies and roof deck | C106: 5413 | D106: sf | E106: 75 | F106: $ / sf | G106: =C106*E106 -> 405975 | H106: =G106/$C$6 -> 27.963562 | I106: =G106/$G$121 -> 0.06214125 | J106: Model: private terraces and balconies 996 sf, PH private roof 1,505 sf, 3rd-floor common terrace 2,467 sf, 2nd-floor rear terrace 444 sf.
A107: Fit-out subtotal | G107: =SUM(G92:G106) -> 1879330 | H107: =G107/$C$6 -> 129.44827 | I107: =G107/$G$121 -> 0.28766282
A109: Site and general | B109: Sidewalk, vault, utilities and site work | C109: 25 | D109: Lf frontage | E109: 850 | F109: $ / Lf | G109: =C109*E109 -> 21250 | H109: =G109/$C$6 -> 1.4637002 | I109: =G109/$G$121 -> 0.0032526672 | J109: South 2nd Street frontage.
A110: Site and general | B110: Environmental remediation allowance | C110: 0 | D110: allowance | E110: 0 | F110: lump sum | G110: =C110*E110 -> 0 | H110: =G110/$C$6 -> 0 | I110: =G110/$G$121 -> 0 | J110: None carried: confirm whether the lot has an E-designation; any cleanup from contingency.
A111: Site and general subtotal | G111: =SUM(G109:G110) -> 21250 | H111: =G111/$C$6 -> 1.4637002 | I111: =G111/$G$121 -> 0.0032526672
A113: Trade costs before general conditions | G113: =(G71+G79+G90+G107+G111)*(1+$C$21) -> 5720959.6 | H113: =G113/$C$6 -> 394.05976 | I113: =G113/$G$121 -> 0.87568836
A115: General conditions | B115: General conditions and GC fee | C115: =G113 -> 5720959.6 | D115: $ of trade | E115: 0.1 | F115: % of trade | G115: =C115*E115 -> 572095.96 | H115: =G115/$C$6 -> 39.405976 | I115: =G115/$G$121 -> 0.087568836 | J115: Contractor's site overhead (supervision, temporary facilities, insurance) plus fee.
...

Sheet Soft Costs
A1: 246 South 2nd Street · Soft Cost Budget
A2: Base: section 1 is the land (acquisition, kept apart from the soft-cost totals); section 2 is construction-period soft costs; section 3 is sponsor wind-down. 8 stories at 85 ft, 9 condos plus a commercial condo, no air rights or certificates.
A3: Blue cells are inputs: change them and every total updates. Black cells are formulas. Rates carry over from the 725 Grand budget unless noted. Every figure is a planning placeholder to be verified.
A5: KEY INPUTS
B6: Total hard cost | C6: ='Hard Costs'!$G$121 -> 6533100 | D6: $ | J6: Linked to the total on the Hard Costs sheet (green = link). Drives the development fee and the warranty reserve.
B7: Land purchase price, 246 South 2nd | C7: 4000000 | D7: $ | J7: Owner, Oct 2026: $4,000,000.
B8: Gross floor area above grade | C8: ='Hard Costs'!$C$6 -> 14518 | D8: gsf | J8: Linked to the Hard Costs sheet (green).
B9: Cellar | C9: ='Hard Costs'!$C$7 -> 3060 | D9: sf | J9: Linked to the Hard Costs sheet (green).
B10: Gross floor area including cellar | C10: =$C$8+$C$9 -> 17578 | D10: gsf | J10: Basis for design and inspection fees.
B11: Condo units | C11: ='Hard Costs'!$C$12 -> 9 | D11: units | J11: Linked to the Hard Costs sheet (green).
B12: Project length | C12: =Finance!$B$10 -> 32 | D12: months | J12: Linked to the Finance sheet (green). Purchase to final unit closing.
B13: Construction period | C13: =Finance!$B$7 -> 20 | D13: months | J13: Linked to the Finance sheet (green). Ground-breaking to completion (TCO). Placeholder until the Gantt chart sets it. Drives builder's risk and construction-period liability insurance.
B14: Owner tax-holding period | C14: 36 | D14: months | J14: Purchase until the condo plan is effective and taxes pass to the condominium. Set to your expected date; 36 months is conservative.
B15: Construction loan amount | C15: =Finance!$B$38 -> 9303306.9 | D15: $ | J15: Linked to the Finance sheet (green). Deck model: 70% of total project cost. Basis for the mortgage recording tax.
B16: Inclusionary Housing certificates purchased | C16: 0 | D16: sf | J16: None: the affordable floor area is the on-site affordable unit (4F).
A18: Section | B18: Line item | C18: Basis | D18: Basis unit | E18: Rate | F18: Rate basis | G18: Total ($) | H18: % of hard | I18: In deck model? | J18: Notes
A19: 1 · ACQUISITION: LAND (shown apart from the soft costs)
A20: Acquisition | B20: Land purchase, 246 South 2nd | C20: =$C$7 -> 4000000 | D20: $ price | E20: 1 | F20: % of price | G20: =C20*E20 -> 4000000 | H20: =G20/$C$6 -> 0.61226676 | I20: Yes | J20: Owner: $4.0M. Change it in the key inputs above. Paid at closing.
A21: Land | G21: =SUM(G20:G20) -> 4000000 | H21: =G21/$C$6 -> 0.61226676
A23: Acquisition | B23: Inclusionary Housing certificates (none) | C23: =$C$16 -> 0 | D23: sf | E23: 200 | F23: $ / sf | G23: =C23*E23 -> 0 | H23: =G23/$C$6 -> 0 | I23: No | J23: Not needed for this design.
A24: IH certificates | G24: =SUM(G23:G23) -> 0 | H24: =G24/$C$6 -> 0
A26: TOTAL ACQUISITION | G26: =G21+G24 -> 4000000 | H26: =G26/$C$6 -> 0.61226676
A28: 2 · CONSTRUCTION-PERIOD SOFT COSTS
A29: Construction | B29: Architecture, structural and MEP engineering | C29: 1 | D29: allowance | E29: 300000 | F29: lump sum | G29: =C29*E29 -> 300000 | H29: =G29/$C$6 -> 0.045920007 | I29: Yes | J29: Owner's 725 Grand figure carried over. Architect of record plus structural, MEP and fire protection engineering through construction administration; the owner's in-house design keeps it below a full-service fee.
A30: Construction | B30: Interior design | C30: 1 | D30: allowance | E30: 40000 | F30: lump sum | G30: =C30*E30 -> 40000 | H30: =G30/$C$6 -> 0.0061226676 | I30: No | J30: Owner's figure, Oct 2026. The deck model has no interior design line yet.
A31: Construction | B31: Expediting, DOB and utility filing fees | C31: 1 | D31: allowance | E31: 45000 | F31: lump sum | G31: =C31*E31 -> 45000 | H31: =G31/$C$6 -> 0.0068880011 | I31: Yes | J31: Owner's figure, Oct 2026.
A32: Construction | B32: Surveys, controlled and special inspections | C32: =$C$10 -> 17578 | D32: gsf | E32: 3.5 | F32: $ / gsf | G32: =C32*E32 -> 61523 | H32: =G32/$C$6 -> 0.009417122 | I32: Yes
A33: Construction | B33: Phase I environmental report | C33: 1 | D33: allowance | E33: 5000 | F33: lump sum | G33: =C33*E33 -> 5000 | H33: =G33/$C$6 -> 0.00076533346 | I33: Yes | J33: Owner, Oct 2026: site not expected to be contaminated; a Phase I is the only investigation budgeted.
A34: Construction | B34: Environmental filings (OER), if the lot has an E-designation | C34: 1 | D34: allowance | E34: 0 | F34: lump sum | G34: =C34*E34 -> 0 | H34: =G34/$C$6 -> 0 | I34: No | J34: None carried: confirm on ZoLa whether 246 South 2nd has an E-designation.
A35: Construction | B35: Energy consultant: energy model, ULEB filing and commissioning | C35: 1 | D35: allowance | E35: 30000 | F35: lump sum | G35: =C35*E35 -> 30000 | H35: =G35/$C$6 -> 0.0045920007 | I35: No | J35: Documents the ULEB energy target that the 5% Zone Green exclusion needs (Passive House level performance); energy model and commissioning.
A36: Construction | B36: Builder's risk insurance | C36: =$C$13 -> 20 | D36: months | E36: 50000 | F36: $ / year | G36: =C36*E36/12 -> 83333.333 | H36: =G36/$C$6 -> 0.012755558 | I36: Yes | J36: Property cover for the building under construction, for the construction period. Placeholder: get a quote.
A37: Construction | B37: General liability insurance during construction | C37: =$C$13 -> 20 | D37: months | E37: 150000 | F37: $ / year | G37: =C37*E37/12 -> 250000 | H37: =G37/$C$6 -> 0.038266673 | I37: Yes | J37: Owner, Oct 15 2026: $125,000/yr covered both builder's risk and GL on a smaller project seven years ago; NYC liability rates have risen sharply since. If the GC's own liability policy is billed in general conditions, check this is not counted twice.
A38: Construction | B38: Owner's property and liability insurance after completion | C38: =$C$12-$C$13 -> 12 | D38: months | E38: 30000 | F38: $ / year | G38: =C38*E38/12 -> 30000 | H38: =G38/$C$6 -> 0.0045920007 | I38: No | J38: From completion until the condo plan is effective and units close (project length less construction period). Placeholder: get a quote.
A39: Construction | B39: Real estate taxes during the owner holding period | C39: =$C$14 -> 36 | D39: months | E39: 67000 | F39: $ / year | G39: =C39*E39/12 -> 201000 | H39: =G39/$C$6 -> 0.030766405 | I39: Yes | J39: 725 Grand's $67,000 a year carried over as a placeholder: replace with 246 South 2nd's DOF bill.
A40: Construction | B40: Legal: acquisition and loan | C40: 1 | D40: allowance | E40: 10000 | F40: lump sum | G40: =C40*E40 -> 10000 | H40: =G40/$C$6 -> 0.0015306669 | I40: Yes | J40: No zoning lot merger, air-rights or easement agreements.
A41: Construction | B41: Offering plan (AG filing) and sponsor legal | C41: 1 | D41: allowance | E41: 60000 | F41: lump sum | G41: =C41*E41 -> 60000 | H41: =G41/$C$6 -> 0.0091840015 | I41: Yes | J41: Condominium with 9 residential units and the commercial condo; includes the affordable unit sale documents.
A42: Construction | B42: Title insurance and recording, land purchase | C42: 1 | D42: allowance | E42: 10000 | F42: lump sum | G42: =C42*E42 -> 10000 | H42: =G42/$C$6 -> 0.0015306669 | I42: Yes | J42: Owner's figure, Oct 2026.
A43: Construction | B43: Development fee | C43: =$C$6 -> 6533100 | D43: $ hard cost | E43: 0.03 | F43: % of hard | G43: =C43*E43 -> 195993 | H43: =G43/$C$6 -> 0.03 | I43: Yes | J43: Sponsor's fee.
A44: Construction | B44: Marketing, branding and sales center | C44: =$C$11 -> 9 | D44: units | E44: 6500 | F44: $ / unit | G44: =C44*E44 -> 58500 | H44: =G44/$C$6 -> 0.0089544014 | I44: Yes
A45: Construction | B45: Appraisal, lender inspections and loan closing | C45: 1 | D45: allowance | E45: 95000 | F45: lump sum | G45: =C45*E45 -> 95000 | H45: =G45/$C$6 -> 0.014541336 | I45: Yes | J45: Loan origination fee and interest are financing costs, not included here.
A46: Subtotal before contingency | G46: =SUM(G29:G45) -> 1475349.3 | H46: =G46/$C$6 -> 0.22582684
A48: Construction | B48: Soft-cost contingency | C48: =G46 -> 1475349.3 | D48: $ of above | E48: 0.05 | F48: % of above | G48: =C48*E48 -> 73767.467 | H48: =G48/$C$6 -> 0.011291342 | I48: Yes
A49: Construction soft costs before recording tax | G49: =G46+G48 -> 1549116.8 | H49: =G49/$C$6 -> 0.23711818
A51: Construction | B51: Mortgage recording tax on the construction loan | C51: =$C$15 -> 9303306.9 | D51: $ loan | E51: 0.028 | F51: % of loan | G51: =C51*E51 -> 260492.59 | H51: =G51/$C$6 -> 0.039872739 | I51: No | J51: NYC + NYS tax on recording the construction mortgage. 2.8% is the usual rate for a loan this size on this property type; confirm with counsel. Not in the deck model.
A52: TOTAL CONSTRUCTION SOFT COSTS | G52: =G49+G51 -> 1809609.4 | H52: =G52/$C$6 -> 0.27699092
A54: 3 · SPONSOR WIND-DOWN AND DISSOLUTION
A55: Wind-down | B55: Condo board turnover: transition engineer report and records | C55: 1 | D55: allowance | E55: 15000 | F55: lump sum | G55: =C55*E55 -> 15000 | H55: =G55/$C$6 -> 0.0022960004 | I55: No
A56: Wind-down | B56: Warranty and punch-list reserve | C56: =$C$6 -> 6533100 | D56: $ hard cost | E56: 0.005 | F56: % of hard | G56: =C56*E56 -> 32665.5 | H56: =G56/$C$6 -> 0.005 | I56: No | J56: Held back for post-closing repairs and claims before distributing profit.
A57: Wind-down | B57: Final audit, final tax returns and K-1s | C57: 1 | D57: allowance | E57: 10000 | F57: lump sum | G57: =C57*E57 -> 10000 | H57: =G57/$C$6 -> 0.0015306669 | I57: No
A58: Wind-down | B58: Entity dissolution filings and legal | C58: 1 | D58: allowance | E58: 5000 | F58: lump sum | G58: =C58*E58 -> 5000 | H58: =G58/$C$6 -> 0.00076533346 | I58: No
A59: Wind-down subtotal | G59: =SUM(G55:G58) -> 62665.5 | H59: =G59/$C$6 -> 0.0095920007
A61: TOTAL SOFT COSTS, ALL SECTIONS | G61: =G52+G59 -> 1872274.9 | H61: =G61/$C$6 -> 0.28658292
A63: MEASURES AND CHECKS
B64: Construction soft costs as % of hard cost | G64: =G52/$C$6 -> 0.27699092
B65: Construction soft costs per unit | F65: $ / unit | G65: =G52/$C$11 -> 201067.71
A67: Base (Oct 18 2026): 246 South 2nd Street on its own 3,100 sf lot in R6 with a commercial overlay: 8 stories at 85 ft (13'-11" ground floor, 11 ft 2nd floor, 10 ft above), plus a cellar and a private roof. 9 condos (8 market-rate and one affordable homeownership unit), 6,879 sellable sf; commercial on the 1st and 2nd floors (4,333 sf sellable) plus 1,857 sf in the cellar; Zone Green (ULEB) 5% exclusion; no air rights or certificates; all-electric.
A68: Not included: land price, hard costs, construction loan interest and origination fee, equity returns, and taxes and common charges on unsold units after the condo plan is effective (the sponsor share, outside this underwriting).
